{
    "Meta Data": {
        "1. Information": "Intraday (60min) open, high, low, close prices and volume - DATA DELAYED BY 15 MINUTES",
        "2. Symbol": "APP",
        "3. Last Refreshed": "2025-12-15 15:00:00",
        "4. Interval": "60min",
        "5. Output Size": "Full size",
        "6. Time Zone": "US/Eastern"
    },
    "Time Series (60min)": {
        "2025-11-28 15:00:00": {
            "1. open": "600.7000",
            "2. high": "601.8600",
            "3. low": "599.4000",
            "4. close": "600.5000",
            "5. volume": "1958"
        },
        "2025-11-28 14:00:00": {
            "1. open": "600.3000",
            "2. high": "601.0000",
            "3. low": "599.4800",
            "4. close": "600.6000",
            "5. volume": "4431"
        },
        "2025-11-28 13:00:00": {
            "1. open": "599.4590",
            "2. high": "602.0200",
            "3. low": "598.5000",
            "4. close": "600.4000",
            "5. volume": "341106"
        },
        "2025-11-28 12:00:00": {
            "1. open": "593.7700",
            "2. high": "599.5900",
            "3. low": "593.0000",
            "4. close": "599.4590",
            "5. volume": "531130"
        },
        "2025-11-28 11:00:00": {
            "1. open": "590.1800",
            "2. high": "596.5000",
            "3. low": "590.1800",
            "4. close": "594.1100",
            "5. volume": "316829"
        },
        "2025-11-28 10:00:00": {
            "1. open": "586.9200",
            "2. high": "592.7700",
            "3. low": "585.6500",
            "4. close": "590.3800",
            "5. volume": "425676"
        },
        "2025-11-26 15:00:00": {
            "1. open": "586.2750",
            "2. high": "588.9400",
            "3. low": "585.4500",
            "4. close": "586.3800",
            "5. volume": "457276"
        },
        "2025-11-26 14:00:00": {
            "1. open": "580.1000",
            "2. high": "586.6900",
            "3. low": "580.1000",
            "4. close": "585.9700",
            "5. volume": "262515"
        },
        "2025-11-26 13:00:00": {
            "1. open": "581.3700",
            "2. high": "584.0550",
            "3. low": "577.5000",
            "4. close": "580.2800",
            "5. volume": "196255"
        },
        "2025-11-26 12:00:00": {
            "1. open": "584.5100",
            "2. high": "585.6100",
            "3. low": "579.8900",
            "4. close": "581.0936",
            "5. volume": "269298"
        },
        "2025-11-26 11:00:00": {
            "1. open": "587.8900",
            "2. high": "589.0000",
            "3. low": "583.8500",
            "4. close": "584.5950",
            "5. volume": "386044"
        },
        "2025-11-26 10:00:00": {
            "1. open": "576.4350",
            "2. high": "590.5400",
            "3. low": "574.0001",
            "4. close": "587.7200",
            "5. volume": "724647"
        },
        "2025-11-25 15:00:00": {
            "1. open": "554.1250",
            "2. high": "557.7700",
            "3. low": "554.0000",
            "4. close": "555.7500",
            "5. volume": "403040"
        },
        "2025-11-25 14:00:00": {
            "1. open": "548.8300",
            "2. high": "554.2300",
            "3. low": "546.7401",
            "4. close": "554.1250",
            "5. volume": "208303"
        },
        "2025-11-25 13:00:00": {
            "1. open": "546.9000",
            "2. high": "549.5600",
            "3. low": "546.4100",
            "4. close": "548.5800",
            "5. volume": "178994"
        },
        "2025-11-25 12:00:00": {
            "1. open": "538.5400",
            "2. high": "550.3600",
            "3. low": "538.5400",
            "4. close": "546.9000",
            "5. volume": "359756"
        },
        "2025-11-25 11:00:00": {
            "1. open": "541.0437",
            "2. high": "541.2200",
            "3. low": "537.0000",
            "4. close": "538.5450",
            "5. volume": "278655"
        },
        "2025-11-25 10:00:00": {
            "1. open": "546.8800",
            "2. high": "548.5500",
            "3. low": "535.8500",
            "4. close": "540.9500",
            "5. volume": "500028"
        },
        "2025-11-24 15:00:00": {
            "1. open": "552.3300",
            "2. high": "564.8000",
            "3. low": "551.8000",
            "4. close": "560.1700",
            "5. volume": "1155995"
        },
        "2025-11-24 14:00:00": {
            "1. open": "551.3800",
            "2. high": "553.4999",
            "3. low": "548.4900",
            "4. close": "552.1400",
            "5. volume": "275917"
        },
        "2025-11-24 13:00:00": {
            "1. open": "551.5500",
            "2. high": "552.7000",
            "3. low": "547.7500",
            "4. close": "551.3900",
            "5. volume": "242145"
        },
        "2025-11-24 12:00:00": {
            "1. open": "549.4300",
            "2. high": "552.4999",
            "3. low": "548.6700",
            "4. close": "551.5499",
            "5. volume": "270719"
        },
        "2025-11-24 11:00:00": {
            "1. open": "543.4050",
            "2. high": "553.7350",
            "3. low": "543.4050",
            "4. close": "549.4300",
            "5. volume": "500509"
        },
        "2025-11-24 10:00:00": {
            "1. open": "538.8700",
            "2. high": "544.7199",
            "3. low": "534.5900",
            "4. close": "543.2000",
            "5. volume": "521454"
        },
        "2025-11-21 15:00:00": {
            "1. open": "524.2000",
            "2. high": "529.9800",
            "3. low": "517.4100",
            "4. close": "520.3900",
            "5. volume": "966702"
        },
        "2025-11-21 14:00:00": {
            "1. open": "519.4000",
            "2. high": "527.3400",
            "3. low": "519.4000",
            "4. close": "524.2000",
            "5. volume": "519031"
        },
        "2025-11-21 13:00:00": {
            "1. open": "516.0400",
            "2. high": "523.5000",
            "3. low": "509.3300",
            "4. close": "519.4200",
            "5. volume": "519967"
        },
        "2025-11-21 12:00:00": {
            "1. open": "512.7200",
            "2. high": "517.5800",
            "3. low": "510.3456",
            "4. close": "516.0250",
            "5. volume": "518232"
        },
        "2025-11-21 11:00:00": {
            "1. open": "495.2300",
            "2. high": "512.8400",
            "3. low": "489.3000",
            "4. close": "512.5750",
            "5. volume": "933986"
        },
        "2025-11-21 10:00:00": {
            "1. open": "509.2000",
            "2. high": "512.4750",
            "3. low": "491.3700",
            "4. close": "495.2300",
            "5. volume": "1345917"
        },
        "2025-11-20 15:00:00": {
            "1. open": "533.0900",
            "2. high": "533.0900",
            "3. low": "519.2000",
            "4. close": "520.8800",
            "5. volume": "648470"
        },
        "2025-11-20 14:00:00": {
            "1. open": "530.2900",
            "2. high": "534.2800",
            "3. low": "527.5500",
            "4. close": "533.2319",
            "5. volume": "331893"
        },
        "2025-11-20 13:00:00": {
            "1. open": "533.1300",
            "2. high": "543.8399",
            "3. low": "527.3018",
            "4. close": "530.2946",
            "5. volume": "500941"
        },
        "2025-11-20 12:00:00": {
            "1. open": "535.0000",
            "2. high": "539.4600",
            "3. low": "525.5000",
            "4. close": "533.2300",
            "5. volume": "649541"
        },
        "2025-11-20 11:00:00": {
            "1. open": "553.5050",
            "2. high": "554.7500",
            "3. low": "534.0600",
            "4. close": "535.4950",
            "5. volume": "715499"
        },
        "2025-11-20 10:00:00": {
            "1. open": "558.2200",
            "2. high": "562.5600",
            "3. low": "552.1300",
            "4. close": "553.5100",
            "5. volume": "640706"
        },
        "2025-11-19 15:00:00": {
            "1. open": "529.5200",
            "2. high": "535.0000",
            "3. low": "527.7600",
            "4. close": "529.7100",
            "5. volume": "695118"
        },
        "2025-11-19 14:00:00": {
            "1. open": "529.7800",
            "2. high": "531.3500",
            "3. low": "527.0000",
            "4. close": "529.8800",
            "5. volume": "332999"
        },
        "2025-11-19 13:00:00": {
            "1. open": "529.8300",
            "2. high": "531.3100",
            "3. low": "525.7400",
            "4. close": "529.4300",
            "5. volume": "325151"
        },
        "2025-11-19 12:00:00": {
            "1. open": "530.0500",
            "2. high": "531.8000",
            "3. low": "525.4300",
            "4. close": "529.7700",
            "5. volume": "335915"
        },
        "2025-11-19 11:00:00": {
            "1. open": "543.4250",
            "2. high": "543.6300",
            "3. low": "528.5501",
            "4. close": "530.1450",
            "5. volume": "443124"
        },
        "2025-11-19 10:00:00": {
            "1. open": "539.5400",
            "2. high": "544.9900",
            "3. low": "537.9900",
            "4. close": "543.4250",
            "5. volume": "486275"
        },
        "2025-11-18 15:00:00": {
            "1. open": "532.4700",
            "2. high": "532.6050",
            "3. low": "522.0000",
            "4. close": "526.3000",
            "5. volume": "928946"
        },
        "2025-11-18 14:00:00": {
            "1. open": "531.9350",
            "2. high": "537.5200",
            "3. low": "531.0000",
            "4. close": "532.5400",
            "5. volume": "244874"
        },
        "2025-11-18 13:00:00": {
            "1. open": "540.2850",
            "2. high": "541.1399",
            "3. low": "531.6000",
            "4. close": "532.2300",
            "5. volume": "335083"
        },
        "2025-11-18 12:00:00": {
            "1. open": "534.9300",
            "2. high": "541.8000",
            "3. low": "531.0600",
            "4. close": "539.7000",
            "5. volume": "440007"
        },
        "2025-11-18 11:00:00": {
            "1. open": "528.8330",
            "2. high": "537.9800",
            "3. low": "525.0000",
            "4. close": "534.8000",
            "5. volume": "382682"
        },
        "2025-11-18 10:00:00": {
            "1. open": "528.7150",
            "2. high": "532.5800",
            "3. low": "523.0400",
            "4. close": "528.2600",
            "5. volume": "608494"
        },
        "2025-11-17 15:00:00": {
            "1. open": "535.2300",
            "2. high": "541.4999",
            "3. low": "532.3100",
            "4. close": "539.2200",
            "5. volume": "842859"
        },
        "2025-11-17 14:00:00": {
            "1. open": "539.8650",
            "2. high": "541.8100",
            "3. low": "533.3300",
            "4. close": "534.8900",
            "5. volume": "372222"
        },
        "2025-11-17 13:00:00": {
            "1. open": "545.6000",
            "2. high": "546.4606",
            "3. low": "538.8500",
            "4. close": "539.4401",
            "5. volume": "404399"
        },
        "2025-11-17 12:00:00": {
            "1. open": "555.4000",
            "2. high": "555.4000",
            "3. low": "545.5300",
            "4. close": "545.6100",
            "5. volume": "266658"
        },
        "2025-11-17 11:00:00": {
            "1. open": "547.2900",
            "2. high": "556.5999",
            "3. low": "544.8200",
            "4. close": "555.5225",
            "5. volume": "416613"
        },
        "2025-11-17 10:00:00": {
            "1. open": "556.5300",
            "2. high": "556.8950",
            "3. low": "539.3800",
            "4. close": "547.1100",
            "5. volume": "665926"
        },
        "2025-11-14 15:00:00": {
            "1. open": "564.8300",
            "2. high": "565.2600",
            "3. low": "557.3400",
            "4. close": "557.7700",
            "5. volume": "526186"
        },
        "2025-11-14 14:00:00": {
            "1. open": "562.8100",
            "2. high": "566.1200",
            "3. low": "561.7600",
            "4. close": "564.5350",
            "5. volume": "193927"
        },
        "2025-11-14 13:00:00": {
            "1. open": "565.0850",
            "2. high": "566.3500",
            "3. low": "559.2200",
            "4. close": "562.6900",
            "5. volume": "247851"
        },
        "2025-11-14 12:00:00": {
            "1. open": "564.2100",
            "2. high": "567.4999",
            "3. low": "562.7500",
            "4. close": "564.8700",
            "5. volume": "253667"
        },
        "2025-11-14 11:00:00": {
            "1. open": "566.5700",
            "2. high": "568.8300",
            "3. low": "560.5500",
            "4. close": "564.2950",
            "5. volume": "494725"
        },
        "2025-11-14 10:00:00": {
            "1. open": "554.7200",
            "2. high": "570.9912",
            "3. low": "547.3000",
            "4. close": "566.3577",
            "5. volume": "1022208"
        },
        "2025-11-13 15:00:00": {
            "1. open": "553.4095",
            "2. high": "560.9700",
            "3. low": "552.7800",
            "4. close": "556.2550",
            "5. volume": "720487"
        },
        "2025-11-13 14:00:00": {
            "1. open": "550.2800",
            "2. high": "555.9986",
            "3. low": "545.6500",
            "4. close": "553.3005",
            "5. volume": "429969"
        },
        "2025-11-13 13:00:00": {
            "1. open": "555.6475",
            "2. high": "556.5000",
            "3. low": "542.4800",
            "4. close": "550.2800",
            "5. volume": "788070"
        },
        "2025-11-13 12:00:00": {
            "1. open": "557.7900",
            "2. high": "563.4499",
            "3. low": "555.3400",
            "4. close": "555.5800",
            "5. volume": "356237"
        },
        "2025-11-13 11:00:00": {
            "1. open": "561.2048",
            "2. high": "562.8451",
            "3. low": "554.7200",
            "4. close": "558.0000",
            "5. volume": "469531"
        },
        "2025-11-13 10:00:00": {
            "1. open": "557.4350",
            "2. high": "564.1800",
            "3. low": "549.2000",
            "4. close": "561.4700",
            "5. volume": "943775"
        },
        "2025-11-12 15:00:00": {
            "1. open": "589.0000",
            "2. high": "589.3300",
            "3. low": "583.2200",
            "4. close": "584.7000",
            "5. volume": "778846"
        },
        "2025-11-12 14:00:00": {
            "1. open": "589.9050",
            "2. high": "591.8700",
            "3. low": "587.7525",
            "4. close": "589.1600",
            "5. volume": "327653"
        },
        "2025-11-12 13:00:00": {
            "1. open": "588.4500",
            "2. high": "590.1100",
            "3. low": "583.4900",
            "4. close": "589.9050",
            "5. volume": "322847"
        },
        "2025-11-12 12:00:00": {
            "1. open": "582.5800",
            "2. high": "589.0000",
            "3. low": "581.2700",
            "4. close": "588.5687",
            "5. volume": "366836"
        },
        "2025-11-12 11:00:00": {
            "1. open": "581.5200",
            "2. high": "588.0710",
            "3. low": "578.0000",
            "4. close": "582.4101",
            "5. volume": "795380"
        },
        "2025-11-12 10:00:00": {
            "1. open": "593.2000",
            "2. high": "593.4899",
            "3. low": "579.2200",
            "4. close": "581.5100",
            "5. volume": "862686"
        },
        "2025-11-11 15:00:00": {
            "1. open": "604.6200",
            "2. high": "605.8500",
            "3. low": "593.3000",
            "4. close": "595.0900",
            "5. volume": "938860"
        },
        "2025-11-11 14:00:00": {
            "1. open": "600.5577",
            "2. high": "605.8500",
            "3. low": "598.0000",
            "4. close": "604.4800",
            "5. volume": "613995"
        },
        "2025-11-11 13:00:00": {
            "1. open": "589.2850",
            "2. high": "600.9600",
            "3. low": "588.0000",
            "4. close": "600.6400",
            "5. volume": "900163"
        },
        "2025-11-11 12:00:00": {
            "1. open": "584.4251",
            "2. high": "592.0000",
            "3. low": "583.0000",
            "4. close": "589.2850",
            "5. volume": "957876"
        },
        "2025-11-11 11:00:00": {
            "1. open": "596.1500",
            "2. high": "596.7500",
            "3. low": "584.1200",
            "4. close": "584.3600",
            "5. volume": "1213951"
        },
        "2025-11-11 10:00:00": {
            "1. open": "617.3200",
            "2. high": "617.6600",
            "3. low": "594.7700",
            "4. close": "596.1100",
            "5. volume": "1599283"
        },
        "2025-11-10 15:00:00": {
            "1. open": "652.8604",
            "2. high": "653.9600",
            "3. low": "648.0100",
            "4. close": "651.3200",
            "5. volume": "620801"
        },
        "2025-11-10 14:00:00": {
            "1. open": "643.9600",
            "2. high": "654.0000",
            "3. low": "643.9100",
            "4. close": "653.0600",
            "5. volume": "341548"
        },
        "2025-11-10 13:00:00": {
            "1. open": "649.5000",
            "2. high": "652.5528",
            "3. low": "642.8000",
            "4. close": "644.1450",
            "5. volume": "391292"
        },
        "2025-11-10 12:00:00": {
            "1. open": "653.8300",
            "2. high": "656.5400",
            "3. low": "648.1000",
            "4. close": "649.2840",
            "5. volume": "288795"
        },
        "2025-11-10 11:00:00": {
            "1. open": "655.0200",
            "2. high": "657.1300",
            "3. low": "647.2912",
            "4. close": "654.3500",
            "5. volume": "511429"
        },
        "2025-11-10 10:00:00": {
            "1. open": "662.0800",
            "2. high": "668.0000",
            "3. low": "654.9000",
            "4. close": "655.6200",
            "5. volume": "736731"
        },
        "2025-11-07 15:00:00": {
            "1. open": "621.2800",
            "2. high": "633.5900",
            "3. low": "615.0200",
            "4. close": "619.7400",
            "5. volume": "1374582"
        },
        "2025-11-07 14:00:00": {
            "1. open": "611.5800",
            "2. high": "621.4700",
            "3. low": "608.0000",
            "4. close": "621.4700",
            "5. volume": "400649"
        },
        "2025-11-07 13:00:00": {
            "1. open": "600.1000",
            "2. high": "615.4399",
            "3. low": "599.8310",
            "4. close": "611.5800",
            "5. volume": "726666"
        },
        "2025-11-07 12:00:00": {
            "1. open": "583.7400",
            "2. high": "601.1100",
            "3. low": "576.4101",
            "4. close": "599.9600",
            "5. volume": "796214"
        },
        "2025-11-07 11:00:00": {
            "1. open": "583.3850",
            "2. high": "589.7929",
            "3. low": "581.3415",
            "4. close": "583.4400",
            "5. volume": "746297"
        },
        "2025-11-07 10:00:00": {
            "1. open": "600.7550",
            "2. high": "601.8500",
            "3. low": "583.0001",
            "4. close": "583.8000",
            "5. volume": "952921"
        },
        "2025-11-06 15:00:00": {
            "1. open": "624.1350",
            "2. high": "625.5500",
            "3. low": "612.1300",
            "4. close": "621.3000",
            "5. volume": "1148470"
        },
        "2025-11-06 14:00:00": {
            "1. open": "630.7400",
            "2. high": "637.9900",
            "3. low": "622.6200",
            "4. close": "624.1350",
            "5. volume": "455236"
        },
        "2025-11-06 13:00:00": {
            "1. open": "626.0600",
            "2. high": "635.5400",
            "3. low": "616.1700",
            "4. close": "630.7700",
            "5. volume": "565779"
        },
        "2025-11-06 12:00:00": {
            "1. open": "629.3183",
            "2. high": "631.7390",
            "3. low": "622.6200",
            "4. close": "626.1850",
            "5. volume": "541640"
        },
        "2025-11-06 11:00:00": {
            "1. open": "630.9200",
            "2. high": "647.9300",
            "3. low": "623.9800",
            "4. close": "629.4942",
            "5. volume": "1062288"
        },
        "2025-11-06 10:00:00": {
            "1. open": "616.1400",
            "2. high": "634.1699",
            "3. low": "611.8000",
            "4. close": "630.9000",
            "5. volume": "1701537"
        },
        "2025-12-05 15:00:00": {
            "1. open": "688.2170",
            "2. high": "693.0000",
            "3. low": "687.0100",
            "4. close": "691.8600",
            "5. volume": "565948"
        },
        "2025-12-05 14:00:00": {
            "1. open": "685.6100",
            "2. high": "689.1400",
            "3. low": "683.2110",
            "4. close": "688.2600",
            "5. volume": "196284"
        },
        "2025-12-05 13:00:00": {
            "1. open": "684.4770",
            "2. high": "689.8990",
            "3. low": "683.2200",
            "4. close": "684.9810",
            "5. volume": "286788"
        },
        "2025-12-05 12:00:00": {
            "1. open": "688.4950",
            "2. high": "688.8800",
            "3. low": "682.3000",
            "4. close": "684.8700",
            "5. volume": "301823"
        },
        "2025-12-05 11:00:00": {
            "1. open": "684.1600",
            "2. high": "689.4200",
            "3. low": "678.6900",
            "4. close": "688.4950",
            "5. volume": "580170"
        },
        "2025-12-05 10:00:00": {
            "1. open": "691.6200",
            "2. high": "700.5999",
            "3. low": "681.7500",
            "4. close": "684.0155",
            "5. volume": "567453"
        },
        "2025-12-04 15:00:00": {
            "1. open": "693.3700",
            "2. high": "693.8599",
            "3. low": "680.1400",
            "4. close": "683.7900",
            "5. volume": "904272"
        },
        "2025-12-04 14:00:00": {
            "1. open": "692.3800",
            "2. high": "693.7499",
            "3. low": "684.0000",
            "4. close": "693.3700",
            "5. volume": "524676"
        },
        "2025-12-04 13:00:00": {
            "1. open": "694.1850",
            "2. high": "698.4700",
            "3. low": "690.3000",
            "4. close": "692.3650",
            "5. volume": "598921"
        },
        "2025-12-04 12:00:00": {
            "1. open": "688.1400",
            "2. high": "694.9500",
            "3. low": "685.6610",
            "4. close": "694.2000",
            "5. volume": "621626"
        },
        "2025-12-04 11:00:00": {
            "1. open": "676.5750",
            "2. high": "689.0000",
            "3. low": "674.2900",
            "4. close": "688.4400",
            "5. volume": "471961"
        },
        "2025-12-04 10:00:00": {
            "1. open": "670.2300",
            "2. high": "685.5000",
            "3. low": "670.1000",
            "4. close": "676.6000",
            "5. volume": "720549"
        },
        "2025-12-03 15:00:00": {
            "1. open": "663.2900",
            "2. high": "663.2900",
            "3. low": "655.6500",
            "4. close": "662.1700",
            "5. volume": "554417"
        },
        "2025-12-03 14:00:00": {
            "1. open": "664.1900",
            "2. high": "665.3600",
            "3. low": "661.2000",
            "4. close": "663.0350",
            "5. volume": "192763"
        },
        "2025-12-03 13:00:00": {
            "1. open": "657.2750",
            "2. high": "667.0900",
            "3. low": "654.5800",
            "4. close": "663.9100",
            "5. volume": "377413"
        },
        "2025-12-03 12:00:00": {
            "1. open": "657.9920",
            "2. high": "661.8900",
            "3. low": "656.3700",
            "4. close": "657.2750",
            "5. volume": "245404"
        },
        "2025-12-03 11:00:00": {
            "1. open": "662.2650",
            "2. high": "663.7500",
            "3. low": "653.6850",
            "4. close": "658.3400",
            "5. volume": "350953"
        },
        "2025-12-03 10:00:00": {
            "1. open": "656.5500",
            "2. high": "662.4100",
            "3. low": "653.6600",
            "4. close": "662.1300",
            "5. volume": "457053"
        },
        "2025-12-02 15:00:00": {
            "1. open": "654.6500",
            "2. high": "657.3650",
            "3. low": "651.4721",
            "4. close": "652.9400",
            "5. volume": "453659"
        },
        "2025-12-02 14:00:00": {
            "1. open": "657.5100",
            "2. high": "659.6300",
            "3. low": "650.6600",
            "4. close": "654.8864",
            "5. volume": "332230"
        },
        "2025-12-02 13:00:00": {
            "1. open": "656.4400",
            "2. high": "665.0000",
            "3. low": "656.3100",
            "4. close": "657.2870",
            "5. volume": "345083"
        },
        "2025-12-02 12:00:00": {
            "1. open": "659.3450",
            "2. high": "661.4300",
            "3. low": "656.4000",
            "4. close": "656.5300",
            "5. volume": "238063"
        },
        "2025-12-02 11:00:00": {
            "1. open": "667.3400",
            "2. high": "671.4090",
            "3. low": "655.2200",
            "4. close": "659.3500",
            "5. volume": "558902"
        },
        "2025-12-02 10:00:00": {
            "1. open": "677.5400",
            "2. high": "679.7000",
            "3. low": "661.4000",
            "4. close": "667.6100",
            "5. volume": "1311678"
        },
        "2025-12-01 15:00:00": {
            "1. open": "617.2600",
            "2. high": "624.7300",
            "3. low": "616.5064",
            "4. close": "624.2800",
            "5. volume": "863222"
        },
        "2025-12-01 14:00:00": {
            "1. open": "619.6150",
            "2. high": "619.7500",
            "3. low": "615.0000",
            "4. close": "617.4450",
            "5. volume": "300497"
        },
        "2025-12-01 13:00:00": {
            "1. open": "619.8550",
            "2. high": "621.3000",
            "3. low": "616.5900",
            "4. close": "619.3500",
            "5. volume": "335574"
        },
        "2025-12-01 12:00:00": {
            "1. open": "617.5050",
            "2. high": "622.4300",
            "3. low": "616.0866",
            "4. close": "619.5400",
            "5. volume": "476287"
        },
        "2025-12-01 11:00:00": {
            "1. open": "605.6280",
            "2. high": "618.3300",
            "3. low": "602.6000",
            "4. close": "617.7000",
            "5. volume": "706371"
        },
        "2025-12-01 10:00:00": {
            "1. open": "594.5600",
            "2. high": "607.1900",
            "3. low": "591.7200",
            "4. close": "605.4200",
            "5. volume": "689773"
        },
        "2025-12-15 15:00:00": {
            "1. open": "685.5400",
            "2. high": "686.7899",
            "3. low": "674.5100",
            "4. close": "675.1700",
            "5. volume": "665034"
        },
        "2025-12-15 14:00:00": {
            "1. open": "688.1000",
            "2. high": "689.3899",
            "3. low": "684.2400",
            "4. close": "686.0300",
            "5. volume": "294908"
        },
        "2025-12-15 13:00:00": {
            "1. open": "688.5700",
            "2. high": "688.8700",
            "3. low": "682.5600",
            "4. close": "688.1000",
            "5. volume": "330600"
        },
        "2025-12-15 12:00:00": {
            "1. open": "686.0000",
            "2. high": "691.7059",
            "3. low": "685.7250",
            "4. close": "688.5804",
            "5. volume": "214704"
        },
        "2025-12-15 11:00:00": {
            "1. open": "684.9800",
            "2. high": "691.8999",
            "3. low": "681.1100",
            "4. close": "686.9000",
            "5. volume": "454796"
        },
        "2025-12-15 10:00:00": {
            "1. open": "664.0150",
            "2. high": "687.6570",
            "3. low": "661.5601",
            "4. close": "684.7700",
            "5. volume": "689499"
        },
        "2025-12-12 15:00:00": {
            "1. open": "676.5400",
            "2. high": "680.0100",
            "3. low": "668.7400",
            "4. close": "670.4600",
            "5. volume": "841845"
        },
        "2025-12-12 14:00:00": {
            "1. open": "684.0800",
            "2. high": "684.2662",
            "3. low": "675.3200",
            "4. close": "676.5600",
            "5. volume": "299884"
        },
        "2025-12-12 13:00:00": {
            "1. open": "683.5950",
            "2. high": "690.4100",
            "3. low": "682.5600",
            "4. close": "684.0800",
            "5. volume": "309003"
        },
        "2025-12-12 12:00:00": {
            "1. open": "679.2500",
            "2. high": "686.3600",
            "3. low": "677.4400",
            "4. close": "683.5635",
            "5. volume": "382607"
        },
        "2025-12-12 11:00:00": {
            "1. open": "685.8400",
            "2. high": "689.5299",
            "3. low": "671.3800",
            "4. close": "679.2400",
            "5. volume": "662122"
        },
        "2025-12-12 10:00:00": {
            "1. open": "702.3800",
            "2. high": "704.4296",
            "3. low": "684.1600",
            "4. close": "685.9802",
            "5. volume": "713372"
        },
        "2025-12-11 15:00:00": {
            "1. open": "721.4650",
            "2. high": "723.4900",
            "3. low": "714.8601",
            "4. close": "716.9000",
            "5. volume": "530879"
        },
        "2025-12-11 14:00:00": {
            "1. open": "716.2500",
            "2. high": "723.0000",
            "3. low": "714.4500",
            "4. close": "721.6600",
            "5. volume": "446790"
        },
        "2025-12-11 13:00:00": {
            "1. open": "710.4400",
            "2. high": "718.2400",
            "3. low": "710.3900",
            "4. close": "716.4000",
            "5. volume": "297576"
        },
        "2025-12-11 12:00:00": {
            "1. open": "707.0000",
            "2. high": "719.8200",
            "3. low": "706.9100",
            "4. close": "710.4301",
            "5. volume": "294866"
        },
        "2025-12-11 11:00:00": {
            "1. open": "716.6400",
            "2. high": "719.0000",
            "3. low": "705.0500",
            "4. close": "707.6010",
            "5. volume": "367869"
        },
        "2025-12-11 10:00:00": {
            "1. open": "703.1000",
            "2. high": "723.1700",
            "3. low": "701.4200",
            "4. close": "716.6400",
            "5. volume": "720108"
        },
        "2025-12-10 15:00:00": {
            "1. open": "715.9900",
            "2. high": "716.7499",
            "3. low": "700.1100",
            "4. close": "703.2200",
            "5. volume": "642085"
        },
        "2025-12-10 14:00:00": {
            "1. open": "702.8800",
            "2. high": "716.4999",
            "3. low": "702.0000",
            "4. close": "715.6950",
            "5. volume": "548323"
        },
        "2025-12-10 13:00:00": {
            "1. open": "703.0400",
            "2. high": "704.5600",
            "3. low": "698.5100",
            "4. close": "702.7505",
            "5. volume": "203280"
        },
        "2025-12-10 12:00:00": {
            "1. open": "707.5000",
            "2. high": "708.6000",
            "3. low": "702.3000",
            "4. close": "703.3600",
            "5. volume": "209503"
        },
        "2025-12-10 11:00:00": {
            "1. open": "702.1400",
            "2. high": "710.2000",
            "3. low": "700.1300",
            "4. close": "707.5050",
            "5. volume": "330690"
        },
        "2025-12-10 10:00:00": {
            "1. open": "710.8800",
            "2. high": "713.4300",
            "3. low": "698.7000",
            "4. close": "702.0288",
            "5. volume": "633320"
        },
        "2025-12-09 15:00:00": {
            "1. open": "720.6500",
            "2. high": "726.8299",
            "3. low": "720.1300",
            "4. close": "724.6100",
            "5. volume": "750695"
        },
        "2025-12-09 14:00:00": {
            "1. open": "719.3200",
            "2. high": "721.5700",
            "3. low": "716.8000",
            "4. close": "720.6450",
            "5. volume": "262797"
        },
        "2025-12-09 13:00:00": {
            "1. open": "718.9313",
            "2. high": "721.5171",
            "3. low": "716.9100",
            "4. close": "719.4650",
            "5. volume": "404593"
        },
        "2025-12-09 12:00:00": {
            "1. open": "716.4700",
            "2. high": "719.8200",
            "3. low": "715.3900",
            "4. close": "718.9000",
            "5. volume": "364605"
        },
        "2025-12-09 11:00:00": {
            "1. open": "713.3200",
            "2. high": "717.3600",
            "3. low": "712.1414",
            "4. close": "716.2751",
            "5. volume": "434710"
        },
        "2025-12-09 10:00:00": {
            "1. open": "706.3901",
            "2. high": "717.0000",
            "3. low": "704.6000",
            "4. close": "713.4700",
            "5. volume": "816240"
        },
        "2025-12-08 15:00:00": {
            "1. open": "689.8850",
            "2. high": "690.0125",
            "3. low": "683.5300",
            "4. close": "689.6500",
            "5. volume": "579416"
        },
        "2025-12-08 14:00:00": {
            "1. open": "692.2300",
            "2. high": "693.3400",
            "3. low": "688.8240",
            "4. close": "689.9500",
            "5. volume": "199037"
        },
        "2025-12-08 13:00:00": {
            "1. open": "696.9050",
            "2. high": "697.8400",
            "3. low": "691.3509",
            "4. close": "692.7000",
            "5. volume": "179194"
        },
        "2025-12-08 12:00:00": {
            "1. open": "696.4000",
            "2. high": "698.3500",
            "3. low": "692.2600",
            "4. close": "696.9050",
            "5. volume": "275237"
        },
        "2025-12-08 11:00:00": {
            "1. open": "703.1850",
            "2. high": "703.1850",
            "3. low": "695.7700",
            "4. close": "696.5600",
            "5. volume": "325578"
        },
        "2025-12-08 10:00:00": {
            "1. open": "699.0000",
            "2. high": "706.6899",
            "3. low": "696.6900",
            "4. close": "703.4830",
            "5. volume": "515712"
        }
    }
}