{
    "Meta Data": {
        "1. Information": "Intraday (60min) open, high, low, close prices and volume - DATA DELAYED BY 15 MINUTES",
        "2. Symbol": "MSTR",
        "3. Last Refreshed": "2025-12-15 15:00:00",
        "4. Interval": "60min",
        "5. Output Size": "Full size",
        "6. Time Zone": "US/Eastern"
    },
    "Time Series (60min)": {
        "2025-11-28 15:00:00": {
            "1. open": "178.0000",
            "2. high": "178.4500",
            "3. low": "177.7500",
            "4. close": "178.3000",
            "5. volume": "34404"
        },
        "2025-11-28 14:00:00": {
            "1. open": "177.6300",
            "2. high": "178.0000",
            "3. low": "177.1800",
            "4. close": "177.9999",
            "5. volume": "43389"
        },
        "2025-11-28 13:00:00": {
            "1. open": "177.1200",
            "2. high": "178.0000",
            "3. low": "175.6400",
            "4. close": "177.6300",
            "5. volume": "1395910"
        },
        "2025-11-28 12:00:00": {
            "1. open": "179.0000",
            "2. high": "179.4200",
            "3. low": "175.0501",
            "4. close": "177.1200",
            "5. volume": "3358770"
        },
        "2025-11-28 11:00:00": {
            "1. open": "183.1400",
            "2. high": "183.3400",
            "3. low": "178.7000",
            "4. close": "178.9950",
            "5. volume": "3088121"
        },
        "2025-11-28 10:00:00": {
            "1. open": "181.8000",
            "2. high": "187.2900",
            "3. low": "181.8000",
            "4. close": "183.0450",
            "5. volume": "4022103"
        },
        "2025-11-26 15:00:00": {
            "1. open": "179.5350",
            "2. high": "179.7400",
            "3. low": "175.5000",
            "4. close": "175.6700",
            "5. volume": "3138730"
        },
        "2025-11-26 14:00:00": {
            "1. open": "180.2600",
            "2. high": "180.6300",
            "3. low": "178.1800",
            "4. close": "179.5600",
            "5. volume": "1755183"
        },
        "2025-11-26 13:00:00": {
            "1. open": "178.0000",
            "2. high": "180.4499",
            "3. low": "177.1800",
            "4. close": "180.2800",
            "5. volume": "3318130"
        },
        "2025-11-26 12:00:00": {
            "1. open": "172.4700",
            "2. high": "178.9354",
            "3. low": "171.8200",
            "4. close": "177.9450",
            "5. volume": "3519003"
        },
        "2025-11-26 11:00:00": {
            "1. open": "171.7200",
            "2. high": "173.3300",
            "3. low": "170.3900",
            "4. close": "172.2700",
            "5. volume": "1565880"
        },
        "2025-11-26 10:00:00": {
            "1. open": "169.9200",
            "2. high": "173.0900",
            "3. low": "169.7000",
            "4. close": "171.6700",
            "5. volume": "1902449"
        },
        "2025-11-25 15:00:00": {
            "1. open": "169.5000",
            "2. high": "172.3450",
            "3. low": "167.6301",
            "4. close": "172.1700",
            "5. volume": "3963786"
        },
        "2025-11-25 14:00:00": {
            "1. open": "170.3100",
            "2. high": "170.4699",
            "3. low": "166.7801",
            "4. close": "169.4900",
            "5. volume": "2782688"
        },
        "2025-11-25 13:00:00": {
            "1. open": "172.2600",
            "2. high": "174.1300",
            "3. low": "169.6100",
            "4. close": "170.3098",
            "5. volume": "2104375"
        },
        "2025-11-25 12:00:00": {
            "1. open": "174.6700",
            "2. high": "176.6100",
            "3. low": "171.8050",
            "4. close": "172.2700",
            "5. volume": "1639027"
        },
        "2025-11-25 11:00:00": {
            "1. open": "172.1450",
            "2. high": "175.5800",
            "3. low": "171.5600",
            "4. close": "174.6750",
            "5. volume": "1700202"
        },
        "2025-11-25 10:00:00": {
            "1. open": "174.2500",
            "2. high": "174.5000",
            "3. low": "170.3930",
            "4. close": "172.1400",
            "5. volume": "2245831"
        },
        "2025-11-24 15:00:00": {
            "1. open": "176.6000",
            "2. high": "179.8400",
            "3. low": "176.6000",
            "4. close": "179.0750",
            "5. volume": "4103075"
        },
        "2025-11-24 14:00:00": {
            "1. open": "177.5600",
            "2. high": "178.4900",
            "3. low": "175.7500",
            "4. close": "176.5700",
            "5. volume": "2260020"
        },
        "2025-11-24 13:00:00": {
            "1. open": "175.9100",
            "2. high": "177.9300",
            "3. low": "175.0000",
            "4. close": "177.6200",
            "5. volume": "2063016"
        },
        "2025-11-24 12:00:00": {
            "1. open": "173.1450",
            "2. high": "176.5500",
            "3. low": "172.6301",
            "4. close": "175.9295",
            "5. volume": "2197885"
        },
        "2025-11-24 11:00:00": {
            "1. open": "173.4000",
            "2. high": "174.9000",
            "3. low": "172.4550",
            "4. close": "173.0501",
            "5. volume": "1685777"
        },
        "2025-11-24 10:00:00": {
            "1. open": "171.6800",
            "2. high": "174.7300",
            "3. low": "170.3000",
            "4. close": "173.3550",
            "5. volume": "2860221"
        },
        "2025-11-21 15:00:00": {
            "1. open": "172.8800",
            "2. high": "173.5900",
            "3. low": "169.5401",
            "4. close": "170.3500",
            "5. volume": "3800198"
        },
        "2025-11-21 14:00:00": {
            "1. open": "173.1100",
            "2. high": "174.3500",
            "3. low": "170.8200",
            "4. close": "172.9200",
            "5. volume": "2436985"
        },
        "2025-11-21 13:00:00": {
            "1. open": "174.2400",
            "2. high": "174.7136",
            "3. low": "169.3000",
            "4. close": "173.0597",
            "5. volume": "2426272"
        },
        "2025-11-21 12:00:00": {
            "1. open": "176.5500",
            "2. high": "176.7100",
            "3. low": "173.3400",
            "4. close": "174.2025",
            "5. volume": "2236687"
        },
        "2025-11-21 11:00:00": {
            "1. open": "168.1300",
            "2. high": "176.7600",
            "3. low": "166.3100",
            "4. close": "176.5900",
            "5. volume": "4094927"
        },
        "2025-11-21 10:00:00": {
            "1. open": "177.4900",
            "2. high": "178.3100",
            "3. low": "167.4401",
            "4. close": "168.0450",
            "5. volume": "5109869"
        },
        "2025-11-20 15:00:00": {
            "1. open": "179.4900",
            "2. high": "180.3400",
            "3. low": "175.6700",
            "4. close": "177.1900",
            "5. volume": "4096458"
        },
        "2025-11-20 14:00:00": {
            "1. open": "172.7400",
            "2. high": "179.7400",
            "3. low": "171.4750",
            "4. close": "179.5200",
            "5. volume": "3952053"
        },
        "2025-11-20 13:00:00": {
            "1. open": "175.9100",
            "2. high": "178.5900",
            "3. low": "171.7800",
            "4. close": "172.8100",
            "5. volume": "2839473"
        },
        "2025-11-20 12:00:00": {
            "1. open": "176.2600",
            "2. high": "178.0300",
            "3. low": "173.0100",
            "4. close": "175.9100",
            "5. volume": "4088534"
        },
        "2025-11-20 11:00:00": {
            "1. open": "182.5800",
            "2. high": "182.9800",
            "3. low": "175.3100",
            "4. close": "176.3900",
            "5. volume": "4799604"
        },
        "2025-11-20 10:00:00": {
            "1. open": "187.9500",
            "2. high": "189.0000",
            "3. low": "182.4700",
            "4. close": "182.6300",
            "5. volume": "3134981"
        },
        "2025-11-19 15:00:00": {
            "1. open": "185.2600",
            "2. high": "188.1150",
            "3. low": "182.6700",
            "4. close": "186.4800",
            "5. volume": "4573106"
        },
        "2025-11-19 14:00:00": {
            "1. open": "184.9350",
            "2. high": "186.8099",
            "3. low": "183.3100",
            "4. close": "185.3250",
            "5. volume": "2614464"
        },
        "2025-11-19 13:00:00": {
            "1. open": "186.4050",
            "2. high": "186.7350",
            "3. low": "181.7300",
            "4. close": "184.9772",
            "5. volume": "3785703"
        },
        "2025-11-19 12:00:00": {
            "1. open": "189.5250",
            "2. high": "190.4000",
            "3. low": "184.0800",
            "4. close": "186.3977",
            "5. volume": "3632282"
        },
        "2025-11-19 11:00:00": {
            "1. open": "189.9000",
            "2. high": "191.5000",
            "3. low": "186.1300",
            "4. close": "189.4900",
            "5. volume": "4136481"
        },
        "2025-11-19 10:00:00": {
            "1. open": "198.8300",
            "2. high": "200.7800",
            "3. low": "189.6900",
            "4. close": "189.9950",
            "5. volume": "3756567"
        },
        "2025-11-18 15:00:00": {
            "1. open": "209.7900",
            "2. high": "212.1384",
            "3. low": "206.5900",
            "4. close": "206.8000",
            "5. volume": "3326341"
        },
        "2025-11-18 14:00:00": {
            "1. open": "210.2350",
            "2. high": "212.9000",
            "3. low": "209.0800",
            "4. close": "209.8050",
            "5. volume": "1602693"
        },
        "2025-11-18 13:00:00": {
            "1. open": "211.0600",
            "2. high": "213.8300",
            "3. low": "209.8100",
            "4. close": "210.2350",
            "5. volume": "1816622"
        },
        "2025-11-18 12:00:00": {
            "1. open": "210.3500",
            "2. high": "211.9400",
            "3. low": "207.1600",
            "4. close": "210.9800",
            "5. volume": "1842768"
        },
        "2025-11-18 11:00:00": {
            "1. open": "207.2100",
            "2. high": "212.9900",
            "3. low": "206.5100",
            "4. close": "210.3501",
            "5. volume": "3221041"
        },
        "2025-11-18 10:00:00": {
            "1. open": "200.6500",
            "2. high": "208.3787",
            "3. low": "199.6500",
            "4. close": "207.4299",
            "5. volume": "3837580"
        },
        "2025-11-17 15:00:00": {
            "1. open": "191.9250",
            "2. high": "195.9000",
            "3. low": "190.9400",
            "4. close": "195.4100",
            "5. volume": "3684770"
        },
        "2025-11-17 14:00:00": {
            "1. open": "193.3150",
            "2. high": "194.3050",
            "3. low": "189.5315",
            "4. close": "191.9150",
            "5. volume": "2538693"
        },
        "2025-11-17 13:00:00": {
            "1. open": "194.2200",
            "2. high": "194.5700",
            "3. low": "191.0600",
            "4. close": "193.2500",
            "5. volume": "1865400"
        },
        "2025-11-17 12:00:00": {
            "1. open": "198.0750",
            "2. high": "201.1600",
            "3. low": "192.6900",
            "4. close": "194.2100",
            "5. volume": "1633909"
        },
        "2025-11-17 11:00:00": {
            "1. open": "196.2100",
            "2. high": "198.1000",
            "3. low": "191.4200",
            "4. close": "198.0900",
            "5. volume": "2058312"
        },
        "2025-11-17 10:00:00": {
            "1. open": "200.2100",
            "2. high": "201.8800",
            "3. low": "195.6300",
            "4. close": "196.2901",
            "5. volume": "2143729"
        },
        "2025-11-14 15:00:00": {
            "1. open": "200.5700",
            "2. high": "201.9600",
            "3. low": "198.3000",
            "4. close": "199.7500",
            "5. volume": "3292256"
        },
        "2025-11-14 14:00:00": {
            "1. open": "198.7159",
            "2. high": "201.0000",
            "3. low": "197.0700",
            "4. close": "200.5300",
            "5. volume": "1670019"
        },
        "2025-11-14 13:00:00": {
            "1. open": "203.3400",
            "2. high": "204.4300",
            "3. low": "198.4395",
            "4. close": "198.9200",
            "5. volume": "1580879"
        },
        "2025-11-14 12:00:00": {
            "1. open": "207.7800",
            "2. high": "208.8400",
            "3. low": "202.6100",
            "4. close": "203.5000",
            "5. volume": "1589202"
        },
        "2025-11-14 11:00:00": {
            "1. open": "203.4300",
            "2. high": "207.8700",
            "3. low": "200.1800",
            "4. close": "207.8250",
            "5. volume": "2495585"
        },
        "2025-11-14 10:00:00": {
            "1. open": "202.2862",
            "2. high": "205.7300",
            "3. low": "194.5600",
            "4. close": "203.3800",
            "5. volume": "4211616"
        },
        "2025-11-13 15:00:00": {
            "1. open": "212.1700",
            "2. high": "212.3500",
            "3. low": "207.0300",
            "4. close": "208.5500",
            "5. volume": "4035780"
        },
        "2025-11-13 14:00:00": {
            "1. open": "211.1300",
            "2. high": "213.4000",
            "3. low": "209.3600",
            "4. close": "212.2500",
            "5. volume": "1478537"
        },
        "2025-11-13 13:00:00": {
            "1. open": "214.1580",
            "2. high": "214.7900",
            "3. low": "209.6041",
            "4. close": "211.0315",
            "5. volume": "1939625"
        },
        "2025-11-13 12:00:00": {
            "1. open": "218.7800",
            "2. high": "219.2600",
            "3. low": "213.9500",
            "4. close": "214.2000",
            "5. volume": "1252281"
        },
        "2025-11-13 11:00:00": {
            "1. open": "219.6400",
            "2. high": "220.3500",
            "3. low": "216.1600",
            "4. close": "218.9200",
            "5. volume": "1385484"
        },
        "2025-11-13 10:00:00": {
            "1. open": "223.0200",
            "2. high": "226.0000",
            "3. low": "218.5000",
            "4. close": "219.7100",
            "5. volume": "1885647"
        },
        "2025-11-12 15:00:00": {
            "1. open": "220.7500",
            "2. high": "225.1700",
            "3. low": "219.8000",
            "4. close": "224.5800",
            "5. volume": "2684022"
        },
        "2025-11-12 14:00:00": {
            "1. open": "223.0800",
            "2. high": "223.3600",
            "3. low": "220.3300",
            "4. close": "220.7365",
            "5. volume": "1044007"
        },
        "2025-11-12 13:00:00": {
            "1. open": "224.2000",
            "2. high": "224.3600",
            "3. low": "221.7001",
            "4. close": "223.0800",
            "5. volume": "918904"
        },
        "2025-11-12 12:00:00": {
            "1. open": "225.2100",
            "2. high": "225.7900",
            "3. low": "222.3501",
            "4. close": "224.1050",
            "5. volume": "1256662"
        },
        "2025-11-12 11:00:00": {
            "1. open": "227.5700",
            "2. high": "228.0000",
            "3. low": "224.1301",
            "4. close": "225.1600",
            "5. volume": "1114284"
        },
        "2025-11-12 10:00:00": {
            "1. open": "233.8000",
            "2. high": "234.1800",
            "3. low": "226.0000",
            "4. close": "227.6100",
            "5. volume": "1363629"
        },
        "2025-11-11 15:00:00": {
            "1. open": "235.1300",
            "2. high": "235.2705",
            "3. low": "230.5500",
            "4. close": "231.1800",
            "5. volume": "2002393"
        },
        "2025-11-11 14:00:00": {
            "1. open": "236.2300",
            "2. high": "236.3801",
            "3. low": "233.4100",
            "4. close": "235.1500",
            "5. volume": "675121"
        },
        "2025-11-11 13:00:00": {
            "1. open": "237.2750",
            "2. high": "238.0500",
            "3. low": "235.6500",
            "4. close": "236.2800",
            "5. volume": "482322"
        },
        "2025-11-11 12:00:00": {
            "1. open": "236.4500",
            "2. high": "237.9000",
            "3. low": "234.1900",
            "4. close": "237.2800",
            "5. volume": "543965"
        },
        "2025-11-11 11:00:00": {
            "1. open": "236.5000",
            "2. high": "239.2400",
            "3. low": "235.3600",
            "4. close": "236.4700",
            "5. volume": "618210"
        },
        "2025-11-11 10:00:00": {
            "1. open": "238.0700",
            "2. high": "238.1500",
            "3. low": "234.2450",
            "4. close": "236.3900",
            "5. volume": "998589"
        },
        "2025-11-10 15:00:00": {
            "1. open": "240.4450",
            "2. high": "241.5999",
            "3. low": "238.5100",
            "4. close": "238.7200",
            "5. volume": "1260941"
        },
        "2025-11-10 14:00:00": {
            "1. open": "238.6200",
            "2. high": "241.8399",
            "3. low": "238.1000",
            "4. close": "240.4500",
            "5. volume": "715699"
        },
        "2025-11-10 13:00:00": {
            "1. open": "241.9000",
            "2. high": "243.0599",
            "3. low": "238.5400",
            "4. close": "238.5700",
            "5. volume": "716525"
        },
        "2025-11-10 12:00:00": {
            "1. open": "238.6900",
            "2. high": "242.7400",
            "3. low": "238.3710",
            "4. close": "241.9263",
            "5. volume": "843447"
        },
        "2025-11-10 11:00:00": {
            "1. open": "235.7000",
            "2. high": "239.3650",
            "3. low": "234.6600",
            "4. close": "238.7100",
            "5. volume": "1113010"
        },
        "2025-11-10 10:00:00": {
            "1. open": "243.1300",
            "2. high": "245.2400",
            "3. low": "234.6000",
            "4. close": "235.8250",
            "5. volume": "1980319"
        },
        "2025-11-07 15:00:00": {
            "1. open": "241.4200",
            "2. high": "243.7325",
            "3. low": "239.1300",
            "4. close": "241.9700",
            "5. volume": "2780898"
        },
        "2025-11-07 14:00:00": {
            "1. open": "238.2081",
            "2. high": "241.5000",
            "3. low": "236.4830",
            "4. close": "241.4700",
            "5. volume": "1257786"
        },
        "2025-11-07 13:00:00": {
            "1. open": "234.6300",
            "2. high": "238.9600",
            "3. low": "233.2100",
            "4. close": "238.2900",
            "5. volume": "1151067"
        },
        "2025-11-07 12:00:00": {
            "1. open": "230.2200",
            "2. high": "234.9500",
            "3. low": "229.4500",
            "4. close": "234.5700",
            "5. volume": "1456668"
        },
        "2025-11-07 11:00:00": {
            "1. open": "227.4650",
            "2. high": "230.5999",
            "3. low": "226.3690",
            "4. close": "230.1300",
            "5. volume": "1010349"
        },
        "2025-11-07 10:00:00": {
            "1. open": "229.3700",
            "2. high": "232.2445",
            "3. low": "225.6800",
            "4. close": "227.4600",
            "5. volume": "2114661"
        },
        "2025-11-06 15:00:00": {
            "1. open": "238.8500",
            "2. high": "240.4500",
            "3. low": "235.0300",
            "4. close": "236.9850",
            "5. volume": "3334683"
        },
        "2025-11-06 14:00:00": {
            "1. open": "240.0100",
            "2. high": "243.4700",
            "3. low": "237.4400",
            "4. close": "238.7300",
            "5. volume": "1022680"
        },
        "2025-11-06 13:00:00": {
            "1. open": "240.6415",
            "2. high": "240.6900",
            "3. low": "237.6200",
            "4. close": "240.0300",
            "5. volume": "916636"
        },
        "2025-11-06 12:00:00": {
            "1. open": "237.6800",
            "2. high": "241.1141",
            "3. low": "237.1076",
            "4. close": "240.5800",
            "5. volume": "1053158"
        },
        "2025-11-06 11:00:00": {
            "1. open": "239.2400",
            "2. high": "242.4600",
            "3. low": "236.8560",
            "4. close": "237.5875",
            "5. volume": "1879145"
        },
        "2025-11-06 10:00:00": {
            "1. open": "245.8500",
            "2. high": "246.1400",
            "3. low": "238.1000",
            "4. close": "239.2600",
            "5. volume": "2249890"
        },
        "2025-12-05 15:00:00": {
            "1. open": "180.5550",
            "2. high": "181.0900",
            "3. low": "178.7500",
            "4. close": "178.9900",
            "5. volume": "2914901"
        },
        "2025-12-05 14:00:00": {
            "1. open": "178.2300",
            "2. high": "180.6700",
            "3. low": "177.6200",
            "4. close": "180.5600",
            "5. volume": "1525815"
        },
        "2025-12-05 13:00:00": {
            "1. open": "179.6300",
            "2. high": "180.4800",
            "3. low": "177.9000",
            "4. close": "178.1400",
            "5. volume": "1436889"
        },
        "2025-12-05 12:00:00": {
            "1. open": "178.6350",
            "2. high": "179.8400",
            "3. low": "177.5950",
            "4. close": "179.6450",
            "5. volume": "1629950"
        },
        "2025-12-05 11:00:00": {
            "1. open": "183.0050",
            "2. high": "183.0500",
            "3. low": "176.3000",
            "4. close": "178.7000",
            "5. volume": "3607480"
        },
        "2025-12-05 10:00:00": {
            "1. open": "179.1450",
            "2. high": "185.3900",
            "3. low": "179.0000",
            "4. close": "183.0300",
            "5. volume": "3131738"
        },
        "2025-12-04 15:00:00": {
            "1. open": "184.9900",
            "2. high": "186.6100",
            "3. low": "184.3200",
            "4. close": "186.1100",
            "5. volume": "2222639"
        },
        "2025-12-04 14:00:00": {
            "1. open": "186.6800",
            "2. high": "186.9900",
            "3. low": "182.3500",
            "4. close": "185.0351",
            "5. volume": "2418163"
        },
        "2025-12-04 13:00:00": {
            "1. open": "187.9900",
            "2. high": "188.1900",
            "3. low": "185.7403",
            "4. close": "186.6550",
            "5. volume": "1259008"
        },
        "2025-12-04 12:00:00": {
            "1. open": "188.7600",
            "2. high": "189.3100",
            "3. low": "186.6000",
            "4. close": "188.0000",
            "5. volume": "1538012"
        },
        "2025-12-04 11:00:00": {
            "1. open": "190.6800",
            "2. high": "190.9099",
            "3. low": "188.1300",
            "4. close": "188.8072",
            "5. volume": "1921318"
        },
        "2025-12-04 10:00:00": {
            "1. open": "184.2800",
            "2. high": "191.0000",
            "3. low": "184.2800",
            "4. close": "190.7300",
            "5. volume": "2786085"
        },
        "2025-12-03 15:00:00": {
            "1. open": "186.5500",
            "2. high": "189.4700",
            "3. low": "185.4500",
            "4. close": "188.3700",
            "5. volume": "3033018"
        },
        "2025-12-03 14:00:00": {
            "1. open": "184.6600",
            "2. high": "187.1400",
            "3. low": "184.5600",
            "4. close": "186.4900",
            "5. volume": "1442456"
        },
        "2025-12-03 13:00:00": {
            "1. open": "186.4801",
            "2. high": "187.2099",
            "3. low": "183.7500",
            "4. close": "184.6950",
            "5. volume": "2585734"
        },
        "2025-12-03 12:00:00": {
            "1. open": "180.8300",
            "2. high": "186.7600",
            "3. low": "180.8100",
            "4. close": "186.5400",
            "5. volume": "2420422"
        },
        "2025-12-03 11:00:00": {
            "1. open": "182.1400",
            "2. high": "185.4200",
            "3. low": "179.0200",
            "4. close": "181.0000",
            "5. volume": "2931271"
        },
        "2025-12-03 10:00:00": {
            "1. open": "185.4000",
            "2. high": "188.3000",
            "3. low": "177.8200",
            "4. close": "182.1700",
            "5. volume": "4152855"
        },
        "2025-12-02 15:00:00": {
            "1. open": "186.8050",
            "2. high": "187.1700",
            "3. low": "181.2400",
            "4. close": "181.2400",
            "5. volume": "5125826"
        },
        "2025-12-02 14:00:00": {
            "1. open": "183.8200",
            "2. high": "188.3700",
            "3. low": "183.6000",
            "4. close": "186.7900",
            "5. volume": "3667447"
        },
        "2025-12-02 13:00:00": {
            "1. open": "181.5700",
            "2. high": "184.9900",
            "3. low": "181.2300",
            "4. close": "183.8400",
            "5. volume": "2370532"
        },
        "2025-12-02 12:00:00": {
            "1. open": "181.1559",
            "2. high": "184.9200",
            "3. low": "181.0100",
            "4. close": "181.6100",
            "5. volume": "2998490"
        },
        "2025-12-02 11:00:00": {
            "1. open": "180.7200",
            "2. high": "182.2300",
            "3. low": "177.3700",
            "4. close": "181.1557",
            "5. volume": "3268331"
        },
        "2025-12-02 10:00:00": {
            "1. open": "182.1100",
            "2. high": "184.1500",
            "3. low": "179.6100",
            "4. close": "180.7520",
            "5. volume": "5262249"
        },
        "2025-12-01 15:00:00": {
            "1. open": "165.7650",
            "2. high": "172.1750",
            "3. low": "165.5500",
            "4. close": "171.4100",
            "5. volume": "8704869"
        },
        "2025-12-01 14:00:00": {
            "1. open": "164.0700",
            "2. high": "165.9000",
            "3. low": "163.1000",
            "4. close": "165.7400",
            "5. volume": "3465770"
        },
        "2025-12-01 13:00:00": {
            "1. open": "159.2500",
            "2. high": "164.1100",
            "3. low": "159.1710",
            "4. close": "164.0350",
            "5. volume": "3850457"
        },
        "2025-12-01 12:00:00": {
            "1. open": "157.2000",
            "2. high": "159.8700",
            "3. low": "155.6100",
            "4. close": "159.2500",
            "5. volume": "4563031"
        },
        "2025-12-01 11:00:00": {
            "1. open": "158.4500",
            "2. high": "159.4000",
            "3. low": "155.8500",
            "4. close": "157.1650",
            "5. volume": "4861449"
        },
        "2025-12-01 10:00:00": {
            "1. open": "165.2690",
            "2. high": "166.1200",
            "3. low": "155.8000",
            "4. close": "158.4520",
            "5. volume": "8701492"
        },
        "2025-12-15 15:00:00": {
            "1. open": "163.8100",
            "2. high": "163.9200",
            "3. low": "160.8600",
            "4. close": "162.0800",
            "5. volume": "4174374"
        },
        "2025-12-15 14:00:00": {
            "1. open": "164.4750",
            "2. high": "165.4800",
            "3. low": "163.5001",
            "4. close": "163.8400",
            "5. volume": "1978782"
        },
        "2025-12-15 13:00:00": {
            "1. open": "162.4500",
            "2. high": "164.6000",
            "3. low": "160.5400",
            "4. close": "164.4700",
            "5. volume": "2349470"
        },
        "2025-12-15 12:00:00": {
            "1. open": "164.7100",
            "2. high": "165.4900",
            "3. low": "162.2201",
            "4. close": "162.4100",
            "5. volume": "2061895"
        },
        "2025-12-15 11:00:00": {
            "1. open": "165.6900",
            "2. high": "167.0500",
            "3. low": "162.6700",
            "4. close": "164.7700",
            "5. volume": "2610765"
        },
        "2025-12-15 10:00:00": {
            "1. open": "168.3600",
            "2. high": "170.6500",
            "3. low": "163.8000",
            "4. close": "165.6150",
            "5. volume": "4397110"
        },
        "2025-12-12 15:00:00": {
            "1. open": "179.3600",
            "2. high": "179.9051",
            "3. low": "176.2200",
            "4. close": "176.4400",
            "5. volume": "3281590"
        },
        "2025-12-12 14:00:00": {
            "1. open": "181.5950",
            "2. high": "181.8000",
            "3. low": "179.1700",
            "4. close": "179.3152",
            "5. volume": "1134169"
        },
        "2025-12-12 13:00:00": {
            "1. open": "180.5000",
            "2. high": "182.6882",
            "3. low": "180.0500",
            "4. close": "181.5950",
            "5. volume": "1386913"
        },
        "2025-12-12 12:00:00": {
            "1. open": "178.0100",
            "2. high": "181.3800",
            "3. low": "177.8400",
            "4. close": "180.5000",
            "5. volume": "1378628"
        },
        "2025-12-12 11:00:00": {
            "1. open": "178.3700",
            "2. high": "180.2600",
            "3. low": "177.1104",
            "4. close": "177.9650",
            "5. volume": "1630961"
        },
        "2025-12-12 10:00:00": {
            "1. open": "183.2600",
            "2. high": "183.7000",
            "3. low": "177.5000",
            "4. close": "178.2700",
            "5. volume": "2403829"
        },
        "2025-12-11 15:00:00": {
            "1. open": "179.9300",
            "2. high": "183.5000",
            "3. low": "179.8307",
            "4. close": "183.3500",
            "5. volume": "3278824"
        },
        "2025-12-11 14:00:00": {
            "1. open": "177.8950",
            "2. high": "181.2500",
            "3. low": "177.7100",
            "4. close": "179.9300",
            "5. volume": "2230577"
        },
        "2025-12-11 13:00:00": {
            "1. open": "174.8300",
            "2. high": "178.6500",
            "3. low": "174.7500",
            "4. close": "177.8950",
            "5. volume": "1908456"
        },
        "2025-12-11 12:00:00": {
            "1. open": "173.9900",
            "2. high": "175.8900",
            "3. low": "173.1850",
            "4. close": "174.8200",
            "5. volume": "1701414"
        },
        "2025-12-11 11:00:00": {
            "1. open": "173.2500",
            "2. high": "174.8000",
            "3. low": "171.4100",
            "4. close": "173.9550",
            "5. volume": "2777506"
        },
        "2025-12-11 10:00:00": {
            "1. open": "174.9200",
            "2. high": "177.8500",
            "3. low": "172.5300",
            "4. close": "173.3025",
            "5. volume": "3185128"
        },
        "2025-12-10 15:00:00": {
            "1. open": "185.4700",
            "2. high": "188.9000",
            "3. low": "182.2000",
            "4. close": "184.5100",
            "5. volume": "5037553"
        },
        "2025-12-10 14:00:00": {
            "1. open": "187.1800",
            "2. high": "191.0700",
            "3. low": "183.0300",
            "4. close": "185.2791",
            "5. volume": "4379683"
        },
        "2025-12-10 13:00:00": {
            "1. open": "186.4450",
            "2. high": "189.2600",
            "3. low": "185.9300",
            "4. close": "187.2650",
            "5. volume": "1491961"
        },
        "2025-12-10 12:00:00": {
            "1. open": "185.9300",
            "2. high": "186.5800",
            "3. low": "184.8500",
            "4. close": "186.4500",
            "5. volume": "1152162"
        },
        "2025-12-10 11:00:00": {
            "1. open": "186.7400",
            "2. high": "187.7500",
            "3. low": "185.2500",
            "4. close": "185.9589",
            "5. volume": "1287269"
        },
        "2025-12-10 10:00:00": {
            "1. open": "186.0000",
            "2. high": "188.4483",
            "3. low": "185.5000",
            "4. close": "186.7000",
            "5. volume": "2415434"
        },
        "2025-12-09 15:00:00": {
            "1. open": "194.4250",
            "2. high": "194.4250",
            "3. low": "188.2700",
            "4. close": "188.9900",
            "5. volume": "3621176"
        },
        "2025-12-09 14:00:00": {
            "1. open": "192.6700",
            "2. high": "194.7800",
            "3. low": "191.3501",
            "4. close": "194.4607",
            "5. volume": "1694628"
        },
        "2025-12-09 13:00:00": {
            "1. open": "193.4002",
            "2. high": "194.3200",
            "3. low": "191.2600",
            "4. close": "192.6700",
            "5. volume": "1807271"
        },
        "2025-12-09 12:00:00": {
            "1. open": "197.3050",
            "2. high": "198.0800",
            "3. low": "192.3900",
            "4. close": "193.3350",
            "5. volume": "3415135"
        },
        "2025-12-09 11:00:00": {
            "1. open": "188.3000",
            "2. high": "198.3999",
            "3. low": "188.2898",
            "4. close": "197.2642",
            "5. volume": "6617320"
        },
        "2025-12-09 10:00:00": {
            "1. open": "182.2100",
            "2. high": "188.4400",
            "3. low": "180.6400",
            "4. close": "188.3850",
            "5. volume": "3435399"
        },
        "2025-12-08 15:00:00": {
            "1. open": "182.7800",
            "2. high": "184.0499",
            "3. low": "182.2000",
            "4. close": "183.6700",
            "5. volume": "2153707"
        },
        "2025-12-08 14:00:00": {
            "1. open": "181.8100",
            "2. high": "183.5800",
            "3. low": "180.8500",
            "4. close": "182.7300",
            "5. volume": "1253229"
        },
        "2025-12-08 13:00:00": {
            "1. open": "184.2100",
            "2. high": "185.0200",
            "3. low": "181.1200",
            "4. close": "181.7900",
            "5. volume": "1521325"
        },
        "2025-12-08 12:00:00": {
            "1. open": "182.8990",
            "2. high": "184.4800",
            "3. low": "181.6500",
            "4. close": "184.2650",
            "5. volume": "1553384"
        },
        "2025-12-08 11:00:00": {
            "1. open": "180.1600",
            "2. high": "184.2000",
            "3. low": "179.2800",
            "4. close": "182.8300",
            "5. volume": "2022811"
        },
        "2025-12-08 10:00:00": {
            "1. open": "182.4400",
            "2. high": "182.7775",
            "3. low": "178.0000",
            "4. close": "180.2400",
            "5. volume": "2869567"
        }
    }
}