{
    "Meta Data": {
        "1. Information": "Intraday (60min) open, high, low, close prices and volume - DATA DELAYED BY 15 MINUTES",
        "2. Symbol": "MRVL",
        "3. Last Refreshed": "2025-12-15 15:00:00",
        "4. Interval": "60min",
        "5. Output Size": "Full size",
        "6. Time Zone": "US/Eastern"
    },
    "Time Series (60min)": {
        "2025-11-28 15:00:00": {
            "1. open": "89.1000",
            "2. high": "89.4500",
            "3. low": "86.3075",
            "4. close": "89.0800",
            "5. volume": "3695"
        },
        "2025-11-28 14:00:00": {
            "1. open": "89.4500",
            "2. high": "91.4355",
            "3. low": "86.3075",
            "4. close": "89.4300",
            "5. volume": "6341"
        },
        "2025-11-28 13:00:00": {
            "1. open": "89.3900",
            "2. high": "89.9200",
            "3. low": "89.3900",
            "4. close": "89.4500",
            "5. volume": "2659499"
        },
        "2025-11-28 12:00:00": {
            "1. open": "89.0600",
            "2. high": "89.5300",
            "3. low": "88.6100",
            "4. close": "89.3900",
            "5. volume": "2965283"
        },
        "2025-11-28 11:00:00": {
            "1. open": "88.8800",
            "2. high": "89.4163",
            "3. low": "88.6450",
            "4. close": "89.0750",
            "5. volume": "1658191"
        },
        "2025-11-28 10:00:00": {
            "1. open": "87.8550",
            "2. high": "88.8999",
            "3. low": "87.3800",
            "4. close": "88.8900",
            "5. volume": "1730062"
        },
        "2025-11-26 15:00:00": {
            "1. open": "89.0400",
            "2. high": "89.3100",
            "3. low": "87.6600",
            "4. close": "87.7100",
            "5. volume": "3360595"
        },
        "2025-11-26 14:00:00": {
            "1. open": "88.6800",
            "2. high": "89.0500",
            "3. low": "88.4727",
            "4. close": "89.0173",
            "5. volume": "1570520"
        },
        "2025-11-26 13:00:00": {
            "1. open": "88.2701",
            "2. high": "88.7400",
            "3. low": "88.1400",
            "4. close": "88.6700",
            "5. volume": "1000967"
        },
        "2025-11-26 12:00:00": {
            "1. open": "87.6600",
            "2. high": "88.6200",
            "3. low": "87.2300",
            "4. close": "88.2900",
            "5. volume": "1296119"
        },
        "2025-11-26 11:00:00": {
            "1. open": "87.0900",
            "2. high": "88.0300",
            "3. low": "87.0800",
            "4. close": "87.6500",
            "5. volume": "1518775"
        },
        "2025-11-26 10:00:00": {
            "1. open": "85.5250",
            "2. high": "87.1650",
            "3. low": "85.3950",
            "4. close": "87.0900",
            "5. volume": "1517145"
        },
        "2025-11-25 15:00:00": {
            "1. open": "82.2750",
            "2. high": "83.8100",
            "3. low": "82.2657",
            "4. close": "83.4000",
            "5. volume": "2327798"
        },
        "2025-11-25 14:00:00": {
            "1. open": "82.2500",
            "2. high": "82.4450",
            "3. low": "81.5800",
            "4. close": "82.2800",
            "5. volume": "1052030"
        },
        "2025-11-25 13:00:00": {
            "1. open": "82.6483",
            "2. high": "82.9300",
            "3. low": "82.2200",
            "4. close": "82.2500",
            "5. volume": "870780"
        },
        "2025-11-25 12:00:00": {
            "1. open": "81.9923",
            "2. high": "83.3400",
            "3. low": "81.9923",
            "4. close": "82.6400",
            "5. volume": "840601"
        },
        "2025-11-25 11:00:00": {
            "1. open": "81.9150",
            "2. high": "82.3600",
            "3. low": "81.6501",
            "4. close": "81.9900",
            "5. volume": "881817"
        },
        "2025-11-25 10:00:00": {
            "1. open": "82.4700",
            "2. high": "82.7000",
            "3. low": "81.2100",
            "4. close": "81.9399",
            "5. volume": "1380780"
        },
        "2025-11-24 15:00:00": {
            "1. open": "82.8750",
            "2. high": "84.5800",
            "3. low": "82.8750",
            "4. close": "83.7700",
            "5. volume": "3974795"
        },
        "2025-11-24 14:00:00": {
            "1. open": "82.7400",
            "2. high": "83.3750",
            "3. low": "82.7400",
            "4. close": "82.8650",
            "5. volume": "1397825"
        },
        "2025-11-24 13:00:00": {
            "1. open": "82.7700",
            "2. high": "83.0300",
            "3. low": "82.6400",
            "4. close": "82.7775",
            "5. volume": "1093376"
        },
        "2025-11-24 12:00:00": {
            "1. open": "81.5750",
            "2. high": "82.8600",
            "3. low": "81.4200",
            "4. close": "82.7700",
            "5. volume": "1092138"
        },
        "2025-11-24 11:00:00": {
            "1. open": "81.0600",
            "2. high": "82.0000",
            "3. low": "81.0600",
            "4. close": "81.5832",
            "5. volume": "1769139"
        },
        "2025-11-24 10:00:00": {
            "1. open": "80.5800",
            "2. high": "81.2700",
            "3. low": "80.1500",
            "4. close": "81.0400",
            "5. volume": "1725134"
        },
        "2025-11-21 15:00:00": {
            "1. open": "78.0150",
            "2. high": "78.8200",
            "3. low": "77.3700",
            "4. close": "77.4300",
            "5. volume": "3336322"
        },
        "2025-11-21 14:00:00": {
            "1. open": "78.2600",
            "2. high": "78.7300",
            "3. low": "77.8400",
            "4. close": "78.0001",
            "5. volume": "1150147"
        },
        "2025-11-21 13:00:00": {
            "1. open": "77.5450",
            "2. high": "78.9168",
            "3. low": "76.5000",
            "4. close": "78.2700",
            "5. volume": "1082027"
        },
        "2025-11-21 12:00:00": {
            "1. open": "77.6700",
            "2. high": "78.3408",
            "3. low": "77.2000",
            "4. close": "77.5300",
            "5. volume": "1271390"
        },
        "2025-11-21 11:00:00": {
            "1. open": "75.4400",
            "2. high": "77.6700",
            "3. low": "74.6750",
            "4. close": "77.6500",
            "5. volume": "2084523"
        },
        "2025-11-21 10:00:00": {
            "1. open": "76.1700",
            "2. high": "76.6400",
            "3. low": "73.6200",
            "4. close": "75.3950",
            "5. volume": "2810411"
        },
        "2025-11-20 15:00:00": {
            "1. open": "78.2200",
            "2. high": "78.2400",
            "3. low": "76.0800",
            "4. close": "76.7000",
            "5. volume": "4304914"
        },
        "2025-11-20 14:00:00": {
            "1. open": "77.9900",
            "2. high": "78.3850",
            "3. low": "77.5300",
            "4. close": "78.2923",
            "5. volume": "1884639"
        },
        "2025-11-20 13:00:00": {
            "1. open": "78.5000",
            "2. high": "80.0500",
            "3. low": "77.6850",
            "4. close": "77.9901",
            "5. volume": "1926629"
        },
        "2025-11-20 12:00:00": {
            "1. open": "79.3400",
            "2. high": "80.0250",
            "3. low": "77.8800",
            "4. close": "78.5300",
            "5. volume": "2477673"
        },
        "2025-11-20 11:00:00": {
            "1. open": "84.0021",
            "2. high": "84.1000",
            "3. low": "79.2150",
            "4. close": "79.3600",
            "5. volume": "3109182"
        },
        "2025-11-20 10:00:00": {
            "1. open": "83.8900",
            "2. high": "84.4400",
            "3. low": "83.5000",
            "4. close": "83.9800",
            "5. volume": "2257786"
        },
        "2025-11-19 15:00:00": {
            "1. open": "80.8000",
            "2. high": "81.8900",
            "3. low": "80.6500",
            "4. close": "81.2800",
            "5. volume": "2792537"
        },
        "2025-11-19 14:00:00": {
            "1. open": "80.2500",
            "2. high": "81.2000",
            "3. low": "79.6922",
            "4. close": "80.8300",
            "5. volume": "1155455"
        },
        "2025-11-19 13:00:00": {
            "1. open": "79.9000",
            "2. high": "80.3600",
            "3. low": "79.5500",
            "4. close": "80.1800",
            "5. volume": "809537"
        },
        "2025-11-19 12:00:00": {
            "1. open": "80.7600",
            "2. high": "80.7600",
            "3. low": "79.4100",
            "4. close": "79.9200",
            "5. volume": "1412024"
        },
        "2025-11-19 11:00:00": {
            "1. open": "80.3200",
            "2. high": "81.0750",
            "3. low": "80.1900",
            "4. close": "80.7600",
            "5. volume": "1241472"
        },
        "2025-11-19 10:00:00": {
            "1. open": "81.0900",
            "2. high": "81.5000",
            "3. low": "80.1700",
            "4. close": "80.3550",
            "5. volume": "1784324"
        },
        "2025-11-18 15:00:00": {
            "1. open": "79.2400",
            "2. high": "79.3900",
            "3. low": "78.4400",
            "4. close": "78.6900",
            "5. volume": "4619720"
        },
        "2025-11-18 14:00:00": {
            "1. open": "79.7200",
            "2. high": "80.1450",
            "3. low": "78.6600",
            "4. close": "79.2556",
            "5. volume": "2147320"
        },
        "2025-11-18 13:00:00": {
            "1. open": "80.8000",
            "2. high": "81.1350",
            "3. low": "79.5500",
            "4. close": "79.7100",
            "5. volume": "1476433"
        },
        "2025-11-18 12:00:00": {
            "1. open": "79.7300",
            "2. high": "81.0200",
            "3. low": "79.0200",
            "4. close": "80.8000",
            "5. volume": "2454777"
        },
        "2025-11-18 11:00:00": {
            "1. open": "79.7550",
            "2. high": "80.2700",
            "3. low": "79.0100",
            "4. close": "79.7300",
            "5. volume": "3066385"
        },
        "2025-11-18 10:00:00": {
            "1. open": "80.7200",
            "2. high": "81.0800",
            "3. low": "79.2500",
            "4. close": "79.7700",
            "5. volume": "3535261"
        },
        "2025-11-17 15:00:00": {
            "1. open": "82.3000",
            "2. high": "83.6950",
            "3. low": "81.8600",
            "4. close": "83.5600",
            "5. volume": "3909370"
        },
        "2025-11-17 14:00:00": {
            "1. open": "83.2100",
            "2. high": "83.3050",
            "3. low": "82.2000",
            "4. close": "82.3100",
            "5. volume": "1588119"
        },
        "2025-11-17 13:00:00": {
            "1. open": "84.0800",
            "2. high": "84.2600",
            "3. low": "83.1599",
            "4. close": "83.2100",
            "5. volume": "1232145"
        },
        "2025-11-17 12:00:00": {
            "1. open": "85.0700",
            "2. high": "85.1200",
            "3. low": "84.0500",
            "4. close": "84.0900",
            "5. volume": "945455"
        },
        "2025-11-17 11:00:00": {
            "1. open": "85.1800",
            "2. high": "85.2521",
            "3. low": "83.9100",
            "4. close": "85.0950",
            "5. volume": "1504338"
        },
        "2025-11-17 10:00:00": {
            "1. open": "86.2900",
            "2. high": "86.3600",
            "3. low": "84.6400",
            "4. close": "85.1150",
            "5. volume": "1432935"
        },
        "2025-11-14 15:00:00": {
            "1. open": "86.9500",
            "2. high": "87.0600",
            "3. low": "85.4100",
            "4. close": "86.4700",
            "5. volume": "2571299"
        },
        "2025-11-14 14:00:00": {
            "1. open": "86.8100",
            "2. high": "87.0382",
            "3. low": "86.3400",
            "4. close": "86.9400",
            "5. volume": "664588"
        },
        "2025-11-14 13:00:00": {
            "1. open": "87.3550",
            "2. high": "87.3800",
            "3. low": "86.2103",
            "4. close": "86.8000",
            "5. volume": "959211"
        },
        "2025-11-14 12:00:00": {
            "1. open": "88.1650",
            "2. high": "88.3750",
            "3. low": "87.0700",
            "4. close": "87.3600",
            "5. volume": "782708"
        },
        "2025-11-14 11:00:00": {
            "1. open": "88.2700",
            "2. high": "88.9000",
            "3. low": "87.3500",
            "4. close": "88.1700",
            "5. volume": "1189885"
        },
        "2025-11-14 10:00:00": {
            "1. open": "88.2800",
            "2. high": "89.0000",
            "3. low": "86.9700",
            "4. close": "88.2250",
            "5. volume": "2069158"
        },
        "2025-11-13 15:00:00": {
            "1. open": "86.4200",
            "2. high": "87.6800",
            "3. low": "86.0500",
            "4. close": "87.6000",
            "5. volume": "3210704"
        },
        "2025-11-13 14:00:00": {
            "1. open": "86.5400",
            "2. high": "87.0800",
            "3. low": "86.0200",
            "4. close": "86.4550",
            "5. volume": "1104748"
        },
        "2025-11-13 13:00:00": {
            "1. open": "86.9750",
            "2. high": "87.2800",
            "3. low": "86.0250",
            "4. close": "86.4950",
            "5. volume": "1616096"
        },
        "2025-11-13 12:00:00": {
            "1. open": "86.8200",
            "2. high": "88.1000",
            "3. low": "86.7700",
            "4. close": "86.9700",
            "5. volume": "1244751"
        },
        "2025-11-13 11:00:00": {
            "1. open": "86.7800",
            "2. high": "87.2300",
            "3. low": "86.3100",
            "4. close": "86.8300",
            "5. volume": "1357675"
        },
        "2025-11-13 10:00:00": {
            "1. open": "86.9650",
            "2. high": "88.4500",
            "3. low": "86.0400",
            "4. close": "86.8200",
            "5. volume": "2716668"
        },
        "2025-11-12 15:00:00": {
            "1. open": "89.4000",
            "2. high": "90.2200",
            "3. low": "89.1200",
            "4. close": "89.3200",
            "5. volume": "2456626"
        },
        "2025-11-12 14:00:00": {
            "1. open": "90.1800",
            "2. high": "90.4900",
            "3. low": "88.8700",
            "4. close": "89.4250",
            "5. volume": "1427302"
        },
        "2025-11-12 13:00:00": {
            "1. open": "91.5000",
            "2. high": "91.6350",
            "3. low": "90.1200",
            "4. close": "90.1900",
            "5. volume": "1382566"
        },
        "2025-11-12 12:00:00": {
            "1. open": "91.7400",
            "2. high": "92.0200",
            "3. low": "91.0300",
            "4. close": "91.5000",
            "5. volume": "899865"
        },
        "2025-11-12 11:00:00": {
            "1. open": "90.9100",
            "2. high": "92.2000",
            "3. low": "90.6500",
            "4. close": "91.7400",
            "5. volume": "954309"
        },
        "2025-11-12 10:00:00": {
            "1. open": "90.8100",
            "2. high": "92.8700",
            "3. low": "90.5400",
            "4. close": "90.8900",
            "5. volume": "1728640"
        },
        "2025-11-11 15:00:00": {
            "1. open": "89.5900",
            "2. high": "89.8550",
            "3. low": "88.9600",
            "4. close": "89.3700",
            "5. volume": "2492667"
        },
        "2025-11-11 14:00:00": {
            "1. open": "90.3550",
            "2. high": "90.4000",
            "3. low": "89.3700",
            "4. close": "89.5700",
            "5. volume": "984653"
        },
        "2025-11-11 13:00:00": {
            "1. open": "90.2000",
            "2. high": "90.5000",
            "3. low": "88.5200",
            "4. close": "90.3700",
            "5. volume": "1652864"
        },
        "2025-11-11 12:00:00": {
            "1. open": "89.8700",
            "2. high": "90.4748",
            "3. low": "89.5001",
            "4. close": "90.2000",
            "5. volume": "769697"
        },
        "2025-11-11 11:00:00": {
            "1. open": "89.9100",
            "2. high": "90.1700",
            "3. low": "88.9882",
            "4. close": "89.8750",
            "5. volume": "1539706"
        },
        "2025-11-11 10:00:00": {
            "1. open": "91.5900",
            "2. high": "92.0800",
            "3. low": "89.4000",
            "4. close": "89.8900",
            "5. volume": "1797449"
        },
        "2025-11-10 15:00:00": {
            "1. open": "93.5100",
            "2. high": "93.7100",
            "3. low": "93.0000",
            "4. close": "93.1900",
            "5. volume": "2463403"
        },
        "2025-11-10 14:00:00": {
            "1. open": "93.3500",
            "2. high": "94.2100",
            "3. low": "93.1400",
            "4. close": "93.5214",
            "5. volume": "1068453"
        },
        "2025-11-10 13:00:00": {
            "1. open": "93.8750",
            "2. high": "93.9900",
            "3. low": "93.3000",
            "4. close": "93.3500",
            "5. volume": "767426"
        },
        "2025-11-10 12:00:00": {
            "1. open": "93.1322",
            "2. high": "93.8850",
            "3. low": "92.9890",
            "4. close": "93.8450",
            "5. volume": "687820"
        },
        "2025-11-10 11:00:00": {
            "1. open": "92.6700",
            "2. high": "93.1900",
            "3. low": "92.1950",
            "4. close": "93.1219",
            "5. volume": "1166833"
        },
        "2025-11-10 10:00:00": {
            "1. open": "93.6450",
            "2. high": "94.4100",
            "3. low": "92.6450",
            "4. close": "92.6500",
            "5. volume": "1606083"
        },
        "2025-11-07 15:00:00": {
            "1. open": "89.6000",
            "2. high": "90.9800",
            "3. low": "89.2300",
            "4. close": "90.9800",
            "5. volume": "3570284"
        },
        "2025-11-07 14:00:00": {
            "1. open": "88.7000",
            "2. high": "89.7400",
            "3. low": "88.4000",
            "4. close": "89.6000",
            "5. volume": "1264439"
        },
        "2025-11-07 13:00:00": {
            "1. open": "86.8900",
            "2. high": "89.0000",
            "3. low": "85.1500",
            "4. close": "88.7150",
            "5. volume": "1639546"
        },
        "2025-11-07 12:00:00": {
            "1. open": "85.5883",
            "2. high": "87.4400",
            "3. low": "85.2900",
            "4. close": "86.8900",
            "5. volume": "1848392"
        },
        "2025-11-07 11:00:00": {
            "1. open": "86.4400",
            "2. high": "87.0500",
            "3. low": "85.1100",
            "4. close": "85.5200",
            "5. volume": "3169924"
        },
        "2025-11-07 10:00:00": {
            "1. open": "90.9400",
            "2. high": "91.0000",
            "3. low": "85.9200",
            "4. close": "86.4000",
            "5. volume": "4409959"
        },
        "2025-11-06 15:00:00": {
            "1. open": "95.7800",
            "2. high": "95.9650",
            "3. low": "93.1650",
            "4. close": "93.3300",
            "5. volume": "4025907"
        },
        "2025-11-06 14:00:00": {
            "1. open": "94.8600",
            "2. high": "96.0200",
            "3. low": "94.6600",
            "4. close": "95.7932",
            "5. volume": "2225190"
        },
        "2025-11-06 13:00:00": {
            "1. open": "94.1150",
            "2. high": "95.4900",
            "3. low": "93.3900",
            "4. close": "94.8500",
            "5. volume": "1727744"
        },
        "2025-11-06 12:00:00": {
            "1. open": "93.2300",
            "2. high": "94.2299",
            "3. low": "92.4201",
            "4. close": "94.1150",
            "5. volume": "1971635"
        },
        "2025-11-06 11:00:00": {
            "1. open": "93.3300",
            "2. high": "94.5900",
            "3. low": "92.9000",
            "4. close": "93.2000",
            "5. volume": "2255022"
        },
        "2025-11-06 10:00:00": {
            "1. open": "95.4350",
            "2. high": "96.0050",
            "3. low": "92.9500",
            "4. close": "93.3301",
            "5. volume": "4915842"
        },
        "2025-12-05 15:00:00": {
            "1. open": "99.1100",
            "2. high": "99.1100",
            "3. low": "98.3100",
            "4. close": "98.8500",
            "5. volume": "3554318"
        },
        "2025-12-05 14:00:00": {
            "1. open": "98.9499",
            "2. high": "99.4900",
            "3. low": "98.7600",
            "4. close": "99.1400",
            "5. volume": "1282222"
        },
        "2025-12-05 13:00:00": {
            "1. open": "99.1000",
            "2. high": "99.1200",
            "3. low": "98.2600",
            "4. close": "98.9350",
            "5. volume": "1199174"
        },
        "2025-12-05 12:00:00": {
            "1. open": "99.7200",
            "2. high": "99.8000",
            "3. low": "97.3100",
            "4. close": "99.1100",
            "5. volume": "3435854"
        },
        "2025-12-05 11:00:00": {
            "1. open": "99.0800",
            "2. high": "100.0000",
            "3. low": "98.6000",
            "4. close": "99.7400",
            "5. volume": "2203163"
        },
        "2025-12-05 10:00:00": {
            "1. open": "100.5100",
            "2. high": "100.6500",
            "3. low": "98.7500",
            "4. close": "99.1318",
            "5. volume": "2896236"
        },
        "2025-12-04 15:00:00": {
            "1. open": "98.3300",
            "2. high": "98.4300",
            "3. low": "97.1800",
            "4. close": "98.2000",
            "5. volume": "3929592"
        },
        "2025-12-04 14:00:00": {
            "1. open": "99.7600",
            "2. high": "99.8650",
            "3. low": "97.3100",
            "4. close": "98.3300",
            "5. volume": "3352431"
        },
        "2025-12-04 13:00:00": {
            "1. open": "99.5600",
            "2. high": "99.9700",
            "3. low": "99.3200",
            "4. close": "99.7750",
            "5. volume": "1187769"
        },
        "2025-12-04 12:00:00": {
            "1. open": "99.7100",
            "2. high": "100.2822",
            "3. low": "99.3700",
            "4. close": "99.5350",
            "5. volume": "1312228"
        },
        "2025-12-04 11:00:00": {
            "1. open": "99.5600",
            "2. high": "100.3600",
            "3. low": "99.0000",
            "4. close": "99.7200",
            "5. volume": "1868987"
        },
        "2025-12-04 10:00:00": {
            "1. open": "99.8600",
            "2. high": "100.3100",
            "3. low": "99.1300",
            "4. close": "99.5900",
            "5. volume": "2817973"
        },
        "2025-12-03 15:00:00": {
            "1. open": "99.6900",
            "2. high": "100.6200",
            "3. low": "99.5308",
            "4. close": "100.2000",
            "5. volume": "5989748"
        },
        "2025-12-03 14:00:00": {
            "1. open": "98.1300",
            "2. high": "99.9356",
            "3. low": "98.0200",
            "4. close": "99.6750",
            "5. volume": "3267275"
        },
        "2025-12-03 13:00:00": {
            "1. open": "96.5860",
            "2. high": "99.0800",
            "3. low": "96.4600",
            "4. close": "98.1400",
            "5. volume": "3629022"
        },
        "2025-12-03 12:00:00": {
            "1. open": "96.3400",
            "2. high": "97.2570",
            "3. low": "95.7900",
            "4. close": "96.6000",
            "5. volume": "3207982"
        },
        "2025-12-03 11:00:00": {
            "1. open": "96.1700",
            "2. high": "97.7733",
            "3. low": "95.9900",
            "4. close": "96.3900",
            "5. volume": "5611935"
        },
        "2025-12-03 10:00:00": {
            "1. open": "99.0550",
            "2. high": "100.1499",
            "3. low": "96.0200",
            "4. close": "96.1800",
            "5. volume": "8492908"
        },
        "2025-12-02 15:00:00": {
            "1. open": "92.9800",
            "2. high": "93.2995",
            "3. low": "92.5650",
            "4. close": "92.8900",
            "5. volume": "5630152"
        },
        "2025-12-02 14:00:00": {
            "1. open": "93.3700",
            "2. high": "93.5499",
            "3. low": "92.7000",
            "4. close": "92.9800",
            "5. volume": "2830775"
        },
        "2025-12-02 13:00:00": {
            "1. open": "92.2550",
            "2. high": "93.3900",
            "3. low": "92.2300",
            "4. close": "93.3700",
            "5. volume": "1740822"
        },
        "2025-12-02 12:00:00": {
            "1. open": "92.3800",
            "2. high": "92.8900",
            "3. low": "92.1950",
            "4. close": "92.2600",
            "5. volume": "1957061"
        },
        "2025-12-02 11:00:00": {
            "1. open": "92.6600",
            "2. high": "93.3400",
            "3. low": "91.4600",
            "4. close": "92.4300",
            "5. volume": "3642414"
        },
        "2025-12-02 10:00:00": {
            "1. open": "93.6800",
            "2. high": "93.8590",
            "3. low": "92.2600",
            "4. close": "92.6844",
            "5. volume": "3473761"
        },
        "2025-12-01 15:00:00": {
            "1. open": "92.1700",
            "2. high": "92.3050",
            "3. low": "90.9600",
            "4. close": "91.1000",
            "5. volume": "2986180"
        },
        "2025-12-01 14:00:00": {
            "1. open": "92.6000",
            "2. high": "92.7400",
            "3. low": "92.0200",
            "4. close": "92.1900",
            "5. volume": "1296871"
        },
        "2025-12-01 13:00:00": {
            "1. open": "91.7200",
            "2. high": "92.7400",
            "3. low": "91.7100",
            "4. close": "92.5933",
            "5. volume": "1231337"
        },
        "2025-12-01 12:00:00": {
            "1. open": "91.5100",
            "2. high": "92.1350",
            "3. low": "91.4400",
            "4. close": "91.7100",
            "5. volume": "2759374"
        },
        "2025-12-01 11:00:00": {
            "1. open": "90.9500",
            "2. high": "91.5250",
            "3. low": "90.6000",
            "4. close": "91.5050",
            "5. volume": "1513402"
        },
        "2025-12-01 10:00:00": {
            "1. open": "91.1150",
            "2. high": "91.2500",
            "3. low": "90.0420",
            "4. close": "90.9600",
            "5. volume": "1959548"
        },
        "2025-12-15 15:00:00": {
            "1. open": "84.7500",
            "2. high": "84.8800",
            "3. low": "84.0200",
            "4. close": "84.3000",
            "5. volume": "2064711"
        },
        "2025-12-15 14:00:00": {
            "1. open": "84.5500",
            "2. high": "84.9100",
            "3. low": "84.4850",
            "4. close": "84.7650",
            "5. volume": "780472"
        },
        "2025-12-15 13:00:00": {
            "1. open": "84.0100",
            "2. high": "84.7000",
            "3. low": "83.6793",
            "4. close": "84.5450",
            "5. volume": "619447"
        },
        "2025-12-15 12:00:00": {
            "1. open": "84.0600",
            "2. high": "84.5100",
            "3. low": "83.7500",
            "4. close": "84.0200",
            "5. volume": "878884"
        },
        "2025-12-15 11:00:00": {
            "1. open": "84.1500",
            "2. high": "84.7700",
            "3. low": "83.8000",
            "4. close": "84.0800",
            "5. volume": "1054417"
        },
        "2025-12-15 10:00:00": {
            "1. open": "84.7950",
            "2. high": "84.9399",
            "3. low": "83.6700",
            "4. close": "84.1506",
            "5. volume": "1749260"
        },
        "2025-12-12 15:00:00": {
            "1. open": "85.0900",
            "2. high": "85.2799",
            "3. low": "83.8899",
            "4. close": "84.4250",
            "5. volume": "4998164"
        },
        "2025-12-12 14:00:00": {
            "1. open": "85.5000",
            "2. high": "85.5890",
            "3. low": "84.9250",
            "4. close": "85.0900",
            "5. volume": "1206014"
        },
        "2025-12-12 13:00:00": {
            "1. open": "85.8300",
            "2. high": "86.5400",
            "3. low": "85.4400",
            "4. close": "85.5129",
            "5. volume": "1033053"
        },
        "2025-12-12 12:00:00": {
            "1. open": "84.7200",
            "2. high": "86.1500",
            "3. low": "84.6700",
            "4. close": "85.8400",
            "5. volume": "1283521"
        },
        "2025-12-12 11:00:00": {
            "1. open": "85.5550",
            "2. high": "85.8800",
            "3. low": "84.2800",
            "4. close": "84.7200",
            "5. volume": "3954415"
        },
        "2025-12-12 10:00:00": {
            "1. open": "87.8900",
            "2. high": "87.9400",
            "3. low": "85.3720",
            "4. close": "85.5500",
            "5. volume": "3040326"
        },
        "2025-12-11 15:00:00": {
            "1. open": "88.8400",
            "2. high": "89.6400",
            "3. low": "88.7941",
            "4. close": "89.4200",
            "5. volume": "2997474"
        },
        "2025-12-11 14:00:00": {
            "1. open": "88.3600",
            "2. high": "89.3700",
            "3. low": "88.3400",
            "4. close": "88.8300",
            "5. volume": "1566667"
        },
        "2025-12-11 13:00:00": {
            "1. open": "88.2000",
            "2. high": "88.8600",
            "3. low": "88.1300",
            "4. close": "88.3800",
            "5. volume": "1128759"
        },
        "2025-12-11 12:00:00": {
            "1. open": "87.9100",
            "2. high": "88.7000",
            "3. low": "87.7000",
            "4. close": "88.2200",
            "5. volume": "1459085"
        },
        "2025-12-11 11:00:00": {
            "1. open": "88.5850",
            "2. high": "88.7500",
            "3. low": "87.5100",
            "4. close": "87.9100",
            "5. volume": "2051618"
        },
        "2025-12-11 10:00:00": {
            "1. open": "89.2000",
            "2. high": "90.0900",
            "3. low": "88.0100",
            "4. close": "88.5900",
            "5. volume": "2470657"
        },
        "2025-12-10 15:00:00": {
            "1. open": "91.7900",
            "2. high": "92.8500",
            "3. low": "91.2500",
            "4. close": "92.4300",
            "5. volume": "4883280"
        },
        "2025-12-10 14:00:00": {
            "1. open": "90.3100",
            "2. high": "91.8200",
            "3. low": "90.2700",
            "4. close": "91.7809",
            "5. volume": "2573208"
        },
        "2025-12-10 13:00:00": {
            "1. open": "91.3200",
            "2. high": "91.3771",
            "3. low": "90.1500",
            "4. close": "90.3300",
            "5. volume": "1398944"
        },
        "2025-12-10 12:00:00": {
            "1. open": "91.1900",
            "2. high": "91.4900",
            "3. low": "90.8300",
            "4. close": "91.3300",
            "5. volume": "1084520"
        },
        "2025-12-10 11:00:00": {
            "1. open": "91.7850",
            "2. high": "91.9600",
            "3. low": "91.0200",
            "4. close": "91.2100",
            "5. volume": "1448699"
        },
        "2025-12-10 10:00:00": {
            "1. open": "91.6800",
            "2. high": "92.4300",
            "3. low": "90.9600",
            "4. close": "91.7601",
            "5. volume": "3470004"
        },
        "2025-12-09 15:00:00": {
            "1. open": "88.8400",
            "2. high": "88.9852",
            "3. low": "88.0400",
            "4. close": "88.8500",
            "5. volume": "5552070"
        },
        "2025-12-09 14:00:00": {
            "1. open": "89.5800",
            "2. high": "89.5800",
            "3. low": "88.6200",
            "4. close": "88.8400",
            "5. volume": "1706742"
        },
        "2025-12-09 13:00:00": {
            "1. open": "89.6200",
            "2. high": "89.8100",
            "3. low": "89.0350",
            "4. close": "89.5900",
            "5. volume": "1469089"
        },
        "2025-12-09 12:00:00": {
            "1. open": "89.2300",
            "2. high": "89.7299",
            "3. low": "88.8801",
            "4. close": "89.6125",
            "5. volume": "1717283"
        },
        "2025-12-09 11:00:00": {
            "1. open": "90.4300",
            "2. high": "90.7700",
            "3. low": "88.7700",
            "4. close": "89.2100",
            "5. volume": "2799071"
        },
        "2025-12-09 10:00:00": {
            "1. open": "89.1500",
            "2. high": "90.9300",
            "3. low": "89.1100",
            "4. close": "90.4350",
            "5. volume": "2461086"
        },
        "2025-12-08 15:00:00": {
            "1. open": "91.5100",
            "2. high": "92.7899",
            "3. low": "89.8999",
            "4. close": "91.9800",
            "5. volume": "6490927"
        },
        "2025-12-08 14:00:00": {
            "1. open": "91.5200",
            "2. high": "92.0500",
            "3. low": "91.1600",
            "4. close": "91.5075",
            "5. volume": "2157941"
        },
        "2025-12-08 13:00:00": {
            "1. open": "92.0800",
            "2. high": "92.2100",
            "3. low": "91.0250",
            "4. close": "91.5230",
            "5. volume": "2826393"
        },
        "2025-12-08 12:00:00": {
            "1. open": "89.7300",
            "2. high": "92.5400",
            "3. low": "89.5200",
            "4. close": "92.1200",
            "5. volume": "5893697"
        },
        "2025-12-08 11:00:00": {
            "1. open": "89.1800",
            "2. high": "90.0900",
            "3. low": "88.9200",
            "4. close": "89.7426",
            "5. volume": "4043996"
        },
        "2025-12-08 10:00:00": {
            "1. open": "89.9585",
            "2. high": "90.6100",
            "3. low": "89.0100",
            "4. close": "89.1900",
            "5. volume": "5266475"
        }
    }
}