{
    "Meta Data": {
        "1. Information": "Intraday (60min) open, high, low, close prices and volume - DATA DELAYED BY 15 MINUTES",
        "2. Symbol": "MCHP",
        "3. Last Refreshed": "2025-12-19 15:00:00",
        "4. Interval": "60min",
        "5. Output Size": "Full size",
        "6. Time Zone": "US/Eastern"
    },
    "Time Series (60min)": {
        "2025-11-28 15:00:00": {
            "1. open": "53.0700",
            "2. high": "54.1465",
            "3. low": "52.6500",
            "4. close": "53.0000",
            "5. volume": "122"
        },
        "2025-11-28 14:00:00": {
            "1. open": "53.5600",
            "2. high": "54.3365",
            "3. low": "52.6400",
            "4. close": "53.4300",
            "5. volume": "163"
        },
        "2025-11-28 13:00:00": {
            "1. open": "53.5800",
            "2. high": "54.5000",
            "3. low": "52.5700",
            "4. close": "52.6400",
            "5. volume": "1787783"
        },
        "2025-11-28 12:00:00": {
            "1. open": "53.6100",
            "2. high": "53.6550",
            "3. low": "53.2800",
            "4. close": "53.5800",
            "5. volume": "1569712"
        },
        "2025-11-28 11:00:00": {
            "1. open": "53.4400",
            "2. high": "53.7400",
            "3. low": "53.3850",
            "4. close": "53.6000",
            "5. volume": "512033"
        },
        "2025-11-28 10:00:00": {
            "1. open": "52.8200",
            "2. high": "53.5400",
            "3. low": "52.8200",
            "4. close": "53.4304",
            "5. volume": "535529"
        },
        "2025-11-26 15:00:00": {
            "1. open": "53.0900",
            "2. high": "53.3600",
            "3. low": "52.5400",
            "4. close": "52.5500",
            "5. volume": "1685752"
        },
        "2025-11-26 14:00:00": {
            "1. open": "52.8600",
            "2. high": "53.1650",
            "3. low": "52.8200",
            "4. close": "53.0900",
            "5. volume": "478347"
        },
        "2025-11-26 13:00:00": {
            "1. open": "52.9300",
            "2. high": "53.0100",
            "3. low": "52.6700",
            "4. close": "52.8650",
            "5. volume": "374417"
        },
        "2025-11-26 12:00:00": {
            "1. open": "52.9200",
            "2. high": "52.9900",
            "3. low": "52.7500",
            "4. close": "52.9200",
            "5. volume": "360060"
        },
        "2025-11-26 11:00:00": {
            "1. open": "52.9400",
            "2. high": "53.2400",
            "3. low": "52.8200",
            "4. close": "52.9200",
            "5. volume": "551309"
        },
        "2025-11-26 10:00:00": {
            "1. open": "52.0300",
            "2. high": "52.9500",
            "3. low": "51.9400",
            "4. close": "52.9400",
            "5. volume": "677774"
        },
        "2025-11-25 15:00:00": {
            "1. open": "51.4000",
            "2. high": "51.8800",
            "3. low": "51.3600",
            "4. close": "51.8000",
            "5. volume": "1681165"
        },
        "2025-11-25 14:00:00": {
            "1. open": "51.3600",
            "2. high": "51.4600",
            "3. low": "51.1700",
            "4. close": "51.3800",
            "5. volume": "658800"
        },
        "2025-11-25 13:00:00": {
            "1. open": "51.7100",
            "2. high": "51.8150",
            "3. low": "51.1900",
            "4. close": "51.3600",
            "5. volume": "566718"
        },
        "2025-11-25 12:00:00": {
            "1. open": "51.7500",
            "2. high": "52.1900",
            "3. low": "51.5900",
            "4. close": "51.7000",
            "5. volume": "556257"
        },
        "2025-11-25 11:00:00": {
            "1. open": "52.0400",
            "2. high": "52.3200",
            "3. low": "51.6000",
            "4. close": "51.7410",
            "5. volume": "748490"
        },
        "2025-11-25 10:00:00": {
            "1. open": "50.6900",
            "2. high": "52.3000",
            "3. low": "50.4750",
            "4. close": "52.0500",
            "5. volume": "1518285"
        },
        "2025-11-24 15:00:00": {
            "1. open": "50.8900",
            "2. high": "51.5100",
            "3. low": "50.7750",
            "4. close": "51.2000",
            "5. volume": "2299789"
        },
        "2025-11-24 14:00:00": {
            "1. open": "51.1600",
            "2. high": "51.3000",
            "3. low": "50.8750",
            "4. close": "50.8800",
            "5. volume": "651076"
        },
        "2025-11-24 13:00:00": {
            "1. open": "51.0300",
            "2. high": "51.3600",
            "3. low": "51.0300",
            "4. close": "51.1600",
            "5. volume": "732212"
        },
        "2025-11-24 12:00:00": {
            "1. open": "50.9300",
            "2. high": "51.1150",
            "3. low": "50.7090",
            "4. close": "51.0151",
            "5. volume": "624050"
        },
        "2025-11-24 11:00:00": {
            "1. open": "50.6700",
            "2. high": "51.0100",
            "3. low": "50.6700",
            "4. close": "50.9362",
            "5. volume": "608027"
        },
        "2025-11-24 10:00:00": {
            "1. open": "50.7300",
            "2. high": "50.8800",
            "3. low": "50.2100",
            "4. close": "50.6550",
            "5. volume": "831116"
        },
        "2025-11-21 15:00:00": {
            "1. open": "50.4719",
            "2. high": "50.9972",
            "3. low": "50.3926",
            "4. close": "50.4917",
            "5. volume": "2669661"
        },
        "2025-11-21 14:00:00": {
            "1. open": "50.5711",
            "2. high": "50.7445",
            "3. low": "50.3530",
            "4. close": "50.4670",
            "5. volume": "1031706"
        },
        "2025-11-21 13:00:00": {
            "1. open": "50.3926",
            "2. high": "50.9477",
            "3. low": "49.8574",
            "4. close": "50.5909",
            "5. volume": "1147616"
        },
        "2025-11-21 12:00:00": {
            "1. open": "50.5859",
            "2. high": "50.6999",
            "3. low": "50.2340",
            "4. close": "50.3926",
            "5. volume": "876878"
        },
        "2025-11-21 11:00:00": {
            "1. open": "48.8463",
            "2. high": "50.5809",
            "3. low": "48.4201",
            "4. close": "50.5611",
            "5. volume": "954728"
        },
        "2025-11-21 10:00:00": {
            "1. open": "48.7472",
            "2. high": "48.9455",
            "3. low": "48.0930",
            "4. close": "48.7869",
            "5. volume": "1165734"
        },
        "2025-11-20 15:00:00": {
            "1. open": "49.1041",
            "2. high": "49.2032",
            "3. low": "48.1426",
            "4. close": "48.5886",
            "5. volume": "2487265"
        },
        "2025-11-20 14:00:00": {
            "1. open": "48.9058",
            "2. high": "49.1437",
            "3. low": "48.6580",
            "4. close": "49.1140",
            "5. volume": "632036"
        },
        "2025-11-20 13:00:00": {
            "1. open": "49.2230",
            "2. high": "50.0060",
            "3. low": "48.7869",
            "4. close": "48.9157",
            "5. volume": "559585"
        },
        "2025-11-20 12:00:00": {
            "1. open": "49.4857",
            "2. high": "49.7682",
            "3. low": "49.0248",
            "4. close": "49.2478",
            "5. volume": "681450"
        },
        "2025-11-20 11:00:00": {
            "1. open": "50.7792",
            "2. high": "50.8287",
            "3. low": "49.4708",
            "4. close": "49.5352",
            "5. volume": "734337"
        },
        "2025-11-20 10:00:00": {
            "1. open": "50.7693",
            "2. high": "51.1261",
            "3. low": "50.5909",
            "4. close": "50.7693",
            "5. volume": "648453"
        },
        "2025-11-19 15:00:00": {
            "1. open": "50.2241",
            "2. high": "50.7296",
            "3. low": "50.1250",
            "4. close": "50.3331",
            "5. volume": "1921857"
        },
        "2025-11-19 14:00:00": {
            "1. open": "50.4025",
            "2. high": "50.4570",
            "3. low": "50.0556",
            "4. close": "50.2340",
            "5. volume": "542847"
        },
        "2025-11-19 13:00:00": {
            "1. open": "50.1646",
            "2. high": "50.5016",
            "3. low": "50.0506",
            "4. close": "50.4025",
            "5. volume": "594455"
        },
        "2025-11-19 12:00:00": {
            "1. open": "50.4818",
            "2. high": "50.5314",
            "3. low": "49.9961",
            "4. close": "50.1944",
            "5. volume": "631354"
        },
        "2025-11-19 11:00:00": {
            "1. open": "50.4620",
            "2. high": "50.6404",
            "3. low": "50.2935",
            "4. close": "50.4868",
            "5. volume": "503977"
        },
        "2025-11-19 10:00:00": {
            "1. open": "50.6107",
            "2. high": "50.9972",
            "3. low": "50.3151",
            "4. close": "50.4670",
            "5. volume": "967666"
        },
        "2025-11-18 15:00:00": {
            "1. open": "50.8585",
            "2. high": "50.9626",
            "3. low": "50.2687",
            "4. close": "50.4124",
            "5. volume": "2004702"
        },
        "2025-11-18 14:00:00": {
            "1. open": "50.8882",
            "2. high": "50.9576",
            "3. low": "50.6057",
            "4. close": "50.8783",
            "5. volume": "582264"
        },
        "2025-11-18 13:00:00": {
            "1. open": "50.9477",
            "2. high": "51.1162",
            "3. low": "50.7594",
            "4. close": "50.8882",
            "5. volume": "681546"
        },
        "2025-11-18 12:00:00": {
            "1. open": "50.4422",
            "2. high": "51.0865",
            "3. low": "50.2241",
            "4. close": "50.9179",
            "5. volume": "938544"
        },
        "2025-11-18 11:00:00": {
            "1. open": "50.2935",
            "2. high": "50.7643",
            "3. low": "50.1646",
            "4. close": "50.4521",
            "5. volume": "856762"
        },
        "2025-11-18 10:00:00": {
            "1. open": "50.3133",
            "2. high": "50.8287",
            "3. low": "50.1795",
            "4. close": "50.3133",
            "5. volume": "1201219"
        },
        "2025-11-17 15:00:00": {
            "1. open": "50.9873",
            "2. high": "51.2649",
            "3. low": "50.4323",
            "4. close": "51.2450",
            "5. volume": "2299644"
        },
        "2025-11-17 14:00:00": {
            "1. open": "51.6217",
            "2. high": "51.6713",
            "3. low": "50.9873",
            "4. close": "50.9972",
            "5. volume": "553480"
        },
        "2025-11-17 13:00:00": {
            "1. open": "51.9884",
            "2. high": "52.0876",
            "3. low": "51.5920",
            "4. close": "51.6415",
            "5. volume": "408489"
        },
        "2025-11-17 12:00:00": {
            "1. open": "52.2561",
            "2. high": "52.3155",
            "3. low": "51.9686",
            "4. close": "52.0033",
            "5. volume": "305097"
        },
        "2025-11-17 11:00:00": {
            "1. open": "51.9884",
            "2. high": "52.2858",
            "3. low": "51.6019",
            "4. close": "52.2561",
            "5. volume": "461026"
        },
        "2025-11-17 10:00:00": {
            "1. open": "52.3849",
            "2. high": "52.7120",
            "3. low": "51.9587",
            "4. close": "51.9785",
            "5. volume": "509005"
        },
        "2025-11-14 15:00:00": {
            "1. open": "52.9499",
            "2. high": "53.2126",
            "3. low": "52.5336",
            "4. close": "53.0292",
            "5. volume": "1792071"
        },
        "2025-11-14 14:00:00": {
            "1. open": "52.9103",
            "2. high": "52.9598",
            "3. low": "52.6228",
            "4. close": "52.9598",
            "5. volume": "414723"
        },
        "2025-11-14 13:00:00": {
            "1. open": "53.3167",
            "2. high": "53.4158",
            "3. low": "52.6674",
            "4. close": "52.9003",
            "5. volume": "634645"
        },
        "2025-11-14 12:00:00": {
            "1. open": "53.9411",
            "2. high": "54.0402",
            "3. low": "53.1382",
            "4. close": "53.3267",
            "5. volume": "440729"
        },
        "2025-11-14 11:00:00": {
            "1. open": "53.8321",
            "2. high": "54.0303",
            "3. low": "53.4951",
            "4. close": "53.9591",
            "5. volume": "541146"
        },
        "2025-11-14 10:00:00": {
            "1. open": "53.6537",
            "2. high": "54.1988",
            "3. low": "53.2274",
            "4. close": "53.7875",
            "5. volume": "675980"
        },
        "2025-11-13 15:00:00": {
            "1. open": "54.0947",
            "2. high": "54.4466",
            "3. low": "53.6537",
            "4. close": "54.3673",
            "5. volume": "2084766"
        },
        "2025-11-13 14:00:00": {
            "1. open": "54.6349",
            "2. high": "54.6647",
            "3. low": "53.9461",
            "4. close": "54.0947",
            "5. volume": "562196"
        },
        "2025-11-13 13:00:00": {
            "1. open": "54.8431",
            "2. high": "54.9819",
            "3. low": "54.4634",
            "4. close": "54.6151",
            "5. volume": "651289"
        },
        "2025-11-13 12:00:00": {
            "1. open": "54.5557",
            "2. high": "55.0017",
            "3. low": "54.4664",
            "4. close": "54.8332",
            "5. volume": "517202"
        },
        "2025-11-13 11:00:00": {
            "1. open": "54.8728",
            "2. high": "55.1702",
            "3. low": "54.3376",
            "4. close": "54.5557",
            "5. volume": "783077"
        },
        "2025-11-13 10:00:00": {
            "1. open": "55.1107",
            "2. high": "55.5865",
            "3. low": "54.5457",
            "4. close": "54.8976",
            "5. volume": "714504"
        },
        "2025-11-12 15:00:00": {
            "1. open": "55.3684",
            "2. high": "55.6311",
            "3. low": "55.0513",
            "4. close": "55.1355",
            "5. volume": "1401793"
        },
        "2025-11-12 14:00:00": {
            "1. open": "55.4973",
            "2. high": "55.5469",
            "3. low": "55.3437",
            "4. close": "55.3783",
            "5. volume": "386165"
        },
        "2025-11-12 13:00:00": {
            "1. open": "55.7699",
            "2. high": "55.8343",
            "3. low": "55.3684",
            "4. close": "55.4973",
            "5. volume": "413487"
        },
        "2025-11-12 12:00:00": {
            "1. open": "55.6906",
            "2. high": "55.7996",
            "3. low": "55.3486",
            "4. close": "55.7748",
            "5. volume": "442115"
        },
        "2025-11-12 11:00:00": {
            "1. open": "55.4378",
            "2. high": "55.8640",
            "3. low": "55.3982",
            "4. close": "55.6906",
            "5. volume": "709231"
        },
        "2025-11-12 10:00:00": {
            "1. open": "56.0028",
            "2. high": "56.1812",
            "3. low": "55.1107",
            "4. close": "55.4279",
            "5. volume": "1153212"
        },
        "2025-11-11 15:00:00": {
            "1. open": "54.3475",
            "2. high": "54.3475",
            "3. low": "53.8172",
            "4. close": "54.2385",
            "5. volume": "1833639"
        },
        "2025-11-11 14:00:00": {
            "1. open": "54.6151",
            "2. high": "54.7043",
            "3. low": "54.1889",
            "4. close": "54.3376",
            "5. volume": "802648"
        },
        "2025-11-11 13:00:00": {
            "1. open": "54.7539",
            "2. high": "55.0116",
            "3. low": "54.4367",
            "4. close": "54.6250",
            "5. volume": "597027"
        },
        "2025-11-11 12:00:00": {
            "1. open": "54.6746",
            "2. high": "54.8976",
            "3. low": "54.4367",
            "4. close": "54.7638",
            "5. volume": "629228"
        },
        "2025-11-11 11:00:00": {
            "1. open": "54.9720",
            "2. high": "54.9720",
            "3. low": "54.3871",
            "4. close": "54.6449",
            "5. volume": "512623"
        },
        "2025-11-11 10:00:00": {
            "1. open": "55.3337",
            "2. high": "55.4279",
            "3. low": "54.5507",
            "4. close": "54.9720",
            "5. volume": "732062"
        },
        "2025-11-10 15:00:00": {
            "1. open": "55.2991",
            "2. high": "55.4775",
            "3. low": "54.8233",
            "4. close": "54.8927",
            "5. volume": "2180631"
        },
        "2025-11-10 14:00:00": {
            "1. open": "55.3387",
            "2. high": "55.5161",
            "3. low": "55.2247",
            "4. close": "55.3040",
            "5. volume": "724845"
        },
        "2025-11-10 13:00:00": {
            "1. open": "55.6261",
            "2. high": "55.6856",
            "3. low": "55.3288",
            "4. close": "55.3486",
            "5. volume": "617730"
        },
        "2025-11-10 12:00:00": {
            "1. open": "55.1999",
            "2. high": "55.7054",
            "3. low": "55.1008",
            "4. close": "55.6311",
            "5. volume": "596368"
        },
        "2025-11-10 11:00:00": {
            "1. open": "55.0513",
            "2. high": "55.3387",
            "3. low": "54.8035",
            "4. close": "55.2098",
            "5. volume": "877447"
        },
        "2025-11-10 10:00:00": {
            "1. open": "55.1157",
            "2. high": "55.5270",
            "3. low": "54.5656",
            "4. close": "55.0513",
            "5. volume": "1302785"
        },
        "2025-11-07 15:00:00": {
            "1. open": "54.8629",
            "2. high": "55.8046",
            "3. low": "54.7192",
            "4. close": "55.8046",
            "5. volume": "3967900"
        },
        "2025-11-07 14:00:00": {
            "1. open": "54.0254",
            "2. high": "54.9868",
            "3. low": "53.8866",
            "4. close": "54.8530",
            "5. volume": "1473151"
        },
        "2025-11-07 13:00:00": {
            "1. open": "53.9808",
            "2. high": "54.3673",
            "3. low": "53.6735",
            "4. close": "54.0303",
            "5. volume": "1376816"
        },
        "2025-11-07 12:00:00": {
            "1. open": "52.9003",
            "2. high": "54.2087",
            "3. low": "52.8310",
            "4. close": "53.9808",
            "5. volume": "1646631"
        },
        "2025-11-07 11:00:00": {
            "1. open": "52.6327",
            "2. high": "53.5694",
            "3. low": "52.3403",
            "4. close": "52.9152",
            "5. volume": "2441578"
        },
        "2025-11-07 10:00:00": {
            "1. open": "55.0513",
            "2. high": "55.0513",
            "3. low": "52.5336",
            "4. close": "52.6228",
            "5. volume": "2909021"
        },
        "2025-11-06 15:00:00": {
            "1. open": "59.6603",
            "2. high": "59.6901",
            "3. low": "58.7088",
            "4. close": "58.8575",
            "5. volume": "2810700"
        },
        "2025-11-06 14:00:00": {
            "1. open": "58.9913",
            "2. high": "59.6851",
            "3. low": "58.9516",
            "4. close": "59.6504",
            "5. volume": "710343"
        },
        "2025-11-06 13:00:00": {
            "1. open": "59.1548",
            "2. high": "59.3729",
            "3. low": "58.7088",
            "4. close": "59.0061",
            "5. volume": "748906"
        },
        "2025-11-06 12:00:00": {
            "1. open": "58.8575",
            "2. high": "59.2341",
            "3. low": "58.6097",
            "4. close": "59.1548",
            "5. volume": "1034772"
        },
        "2025-11-06 11:00:00": {
            "1. open": "59.5612",
            "2. high": "60.0667",
            "3. low": "58.7088",
            "4. close": "58.8475",
            "5. volume": "1002509"
        },
        "2025-11-06 10:00:00": {
            "1. open": "60.2699",
            "2. high": "60.4186",
            "3. low": "59.5017",
            "4. close": "59.5463",
            "5. volume": "936491"
        },
        "2025-12-05 15:00:00": {
            "1. open": "66.8100",
            "2. high": "66.9200",
            "3. low": "65.5955",
            "4. close": "65.7800",
            "5. volume": "2526177"
        },
        "2025-12-05 14:00:00": {
            "1. open": "66.2500",
            "2. high": "66.8600",
            "3. low": "66.1700",
            "4. close": "66.8200",
            "5. volume": "697516"
        },
        "2025-12-05 13:00:00": {
            "1. open": "66.1000",
            "2. high": "66.3300",
            "3. low": "65.7800",
            "4. close": "66.2300",
            "5. volume": "1077882"
        },
        "2025-12-05 12:00:00": {
            "1. open": "66.4600",
            "2. high": "66.4700",
            "3. low": "65.9600",
            "4. close": "66.1100",
            "5. volume": "815289"
        },
        "2025-12-05 11:00:00": {
            "1. open": "66.5000",
            "2. high": "66.9500",
            "3. low": "66.0801",
            "4. close": "66.4650",
            "5. volume": "1754713"
        },
        "2025-12-05 10:00:00": {
            "1. open": "66.3700",
            "2. high": "66.7400",
            "3. low": "66.2100",
            "4. close": "66.4900",
            "5. volume": "1313842"
        },
        "2025-12-04 15:00:00": {
            "1. open": "64.3300",
            "2. high": "64.8300",
            "3. low": "63.8300",
            "4. close": "64.7390",
            "5. volume": "2674507"
        },
        "2025-12-04 14:00:00": {
            "1. open": "65.2450",
            "2. high": "65.4200",
            "3. low": "64.2600",
            "4. close": "64.3400",
            "5. volume": "1596756"
        },
        "2025-12-04 13:00:00": {
            "1. open": "65.0000",
            "2. high": "65.4850",
            "3. low": "64.9050",
            "4. close": "65.2600",
            "5. volume": "1208981"
        },
        "2025-12-04 12:00:00": {
            "1. open": "64.5500",
            "2. high": "65.1400",
            "3. low": "64.3800",
            "4. close": "65.0100",
            "5. volume": "1055119"
        },
        "2025-12-04 11:00:00": {
            "1. open": "63.7400",
            "2. high": "64.6750",
            "3. low": "63.7100",
            "4. close": "64.5600",
            "5. volume": "1027620"
        },
        "2025-12-04 10:00:00": {
            "1. open": "63.7200",
            "2. high": "63.9600",
            "3. low": "63.4400",
            "4. close": "63.7600",
            "5. volume": "1127518"
        },
        "2025-12-03 15:00:00": {
            "1. open": "62.3200",
            "2. high": "63.9400",
            "3. low": "62.2400",
            "4. close": "63.6200",
            "5. volume": "4586719"
        },
        "2025-12-03 14:00:00": {
            "1. open": "62.2450",
            "2. high": "62.5300",
            "3. low": "62.0500",
            "4. close": "62.3100",
            "5. volume": "1270597"
        },
        "2025-12-03 13:00:00": {
            "1. open": "61.7600",
            "2. high": "62.4000",
            "3. low": "61.4650",
            "4. close": "62.2450",
            "5. volume": "1332699"
        },
        "2025-12-03 12:00:00": {
            "1. open": "62.1700",
            "2. high": "62.4800",
            "3. low": "61.7150",
            "4. close": "61.7600",
            "5. volume": "1419762"
        },
        "2025-12-03 11:00:00": {
            "1. open": "60.8826",
            "2. high": "62.2600",
            "3. low": "60.7200",
            "4. close": "62.1800",
            "5. volume": "2085782"
        },
        "2025-12-03 10:00:00": {
            "1. open": "61.6400",
            "2. high": "62.2900",
            "3. low": "60.7300",
            "4. close": "60.8900",
            "5. volume": "2791389"
        },
        "2025-12-02 15:00:00": {
            "1. open": "56.8200",
            "2. high": "57.3500",
            "3. low": "56.6500",
            "4. close": "56.7200",
            "5. volume": "3672339"
        },
        "2025-12-02 14:00:00": {
            "1. open": "55.7200",
            "2. high": "56.8400",
            "3. low": "55.6650",
            "4. close": "56.8150",
            "5. volume": "1232762"
        },
        "2025-12-02 13:00:00": {
            "1. open": "55.0700",
            "2. high": "55.7700",
            "3. low": "55.0400",
            "4. close": "55.7300",
            "5. volume": "680550"
        },
        "2025-12-02 12:00:00": {
            "1. open": "54.8400",
            "2. high": "55.3800",
            "3. low": "54.8300",
            "4. close": "55.0700",
            "5. volume": "658270"
        },
        "2025-12-02 11:00:00": {
            "1. open": "54.6800",
            "2. high": "54.8785",
            "3. low": "54.2200",
            "4. close": "54.8600",
            "5. volume": "823057"
        },
        "2025-12-02 10:00:00": {
            "1. open": "53.7700",
            "2. high": "54.7450",
            "3. low": "53.5850",
            "4. close": "54.6900",
            "5. volume": "716573"
        },
        "2025-12-01 15:00:00": {
            "1. open": "53.5200",
            "2. high": "53.7200",
            "3. low": "53.3500",
            "4. close": "53.4300",
            "5. volume": "1243018"
        },
        "2025-12-01 14:00:00": {
            "1. open": "53.8600",
            "2. high": "53.8600",
            "3. low": "53.3763",
            "4. close": "53.5300",
            "5. volume": "363867"
        },
        "2025-12-01 13:00:00": {
            "1. open": "54.1700",
            "2. high": "54.2500",
            "3. low": "53.8300",
            "4. close": "53.8700",
            "5. volume": "270446"
        },
        "2025-12-01 12:00:00": {
            "1. open": "54.0700",
            "2. high": "54.2700",
            "3. low": "54.0000",
            "4. close": "54.1500",
            "5. volume": "258441"
        },
        "2025-12-01 11:00:00": {
            "1. open": "53.9020",
            "2. high": "54.1400",
            "3. low": "53.8800",
            "4. close": "54.0750",
            "5. volume": "447518"
        },
        "2025-12-01 10:00:00": {
            "1. open": "53.8000",
            "2. high": "53.9200",
            "3. low": "53.4600",
            "4. close": "53.8950",
            "5. volume": "540149"
        },
        "2025-12-15 15:00:00": {
            "1. open": "67.5700",
            "2. high": "67.5950",
            "3. low": "66.8700",
            "4. close": "67.1900",
            "5. volume": "1481626"
        },
        "2025-12-15 14:00:00": {
            "1. open": "67.3800",
            "2. high": "67.6000",
            "3. low": "67.1700",
            "4. close": "67.5800",
            "5. volume": "451438"
        },
        "2025-12-15 13:00:00": {
            "1. open": "66.7400",
            "2. high": "67.4150",
            "3. low": "66.6700",
            "4. close": "67.3800",
            "5. volume": "470498"
        },
        "2025-12-15 12:00:00": {
            "1. open": "67.1300",
            "2. high": "67.3850",
            "3. low": "66.6750",
            "4. close": "66.7400",
            "5. volume": "707384"
        },
        "2025-12-15 11:00:00": {
            "1. open": "66.8450",
            "2. high": "67.1700",
            "3. low": "66.5200",
            "4. close": "67.1299",
            "5. volume": "512635"
        },
        "2025-12-15 10:00:00": {
            "1. open": "67.2550",
            "2. high": "67.2800",
            "3. low": "66.5400",
            "4. close": "66.8500",
            "5. volume": "602846"
        },
        "2025-12-12 15:00:00": {
            "1. open": "67.3800",
            "2. high": "67.5700",
            "3. low": "66.6300",
            "4. close": "67.1800",
            "5. volume": "1905730"
        },
        "2025-12-12 14:00:00": {
            "1. open": "67.9300",
            "2. high": "67.9700",
            "3. low": "67.1100",
            "4. close": "67.3700",
            "5. volume": "679770"
        },
        "2025-12-12 13:00:00": {
            "1. open": "67.7300",
            "2. high": "68.1800",
            "3. low": "67.6800",
            "4. close": "67.9200",
            "5. volume": "518119"
        },
        "2025-12-12 12:00:00": {
            "1. open": "67.4700",
            "2. high": "68.0800",
            "3. low": "67.4300",
            "4. close": "67.7300",
            "5. volume": "493021"
        },
        "2025-12-12 11:00:00": {
            "1. open": "67.8700",
            "2. high": "68.0300",
            "3. low": "67.0950",
            "4. close": "67.4800",
            "5. volume": "3005939"
        },
        "2025-12-12 10:00:00": {
            "1. open": "69.2800",
            "2. high": "69.3400",
            "3. low": "67.7000",
            "4. close": "67.8950",
            "5. volume": "1060756"
        },
        "2025-12-11 15:00:00": {
            "1. open": "68.4900",
            "2. high": "69.2700",
            "3. low": "68.3700",
            "4. close": "69.1000",
            "5. volume": "2333531"
        },
        "2025-12-11 14:00:00": {
            "1. open": "67.7800",
            "2. high": "68.4900",
            "3. low": "67.7300",
            "4. close": "68.4900",
            "5. volume": "764986"
        },
        "2025-12-11 13:00:00": {
            "1. open": "67.7900",
            "2. high": "67.9400",
            "3. low": "67.6700",
            "4. close": "67.7800",
            "5. volume": "455187"
        },
        "2025-12-11 12:00:00": {
            "1. open": "67.9800",
            "2. high": "68.3200",
            "3. low": "67.7900",
            "4. close": "67.7942",
            "5. volume": "523544"
        },
        "2025-12-11 11:00:00": {
            "1. open": "68.1100",
            "2. high": "68.2600",
            "3. low": "67.6800",
            "4. close": "67.9700",
            "5. volume": "640325"
        },
        "2025-12-11 10:00:00": {
            "1. open": "67.1300",
            "2. high": "68.4000",
            "3. low": "66.7800",
            "4. close": "68.1100",
            "5. volume": "1159086"
        },
        "2025-12-10 15:00:00": {
            "1. open": "67.7300",
            "2. high": "68.1999",
            "3. low": "67.4200",
            "4. close": "67.9000",
            "5. volume": "2114895"
        },
        "2025-12-10 14:00:00": {
            "1. open": "67.0600",
            "2. high": "67.7650",
            "3. low": "66.6650",
            "4. close": "67.7200",
            "5. volume": "755952"
        },
        "2025-12-10 13:00:00": {
            "1. open": "66.8600",
            "2. high": "67.0850",
            "3. low": "66.7418",
            "4. close": "67.0500",
            "5. volume": "395277"
        },
        "2025-12-10 12:00:00": {
            "1. open": "67.1200",
            "2. high": "67.1400",
            "3. low": "66.7700",
            "4. close": "66.8700",
            "5. volume": "281644"
        },
        "2025-12-10 11:00:00": {
            "1. open": "67.2950",
            "2. high": "67.3750",
            "3. low": "67.0500",
            "4. close": "67.1100",
            "5. volume": "1025155"
        },
        "2025-12-10 10:00:00": {
            "1. open": "67.2750",
            "2. high": "67.5700",
            "3. low": "66.9100",
            "4. close": "67.2900",
            "5. volume": "501843"
        },
        "2025-12-09 15:00:00": {
            "1. open": "67.2900",
            "2. high": "67.3900",
            "3. low": "66.7050",
            "4. close": "66.8600",
            "5. volume": "1709896"
        },
        "2025-12-09 14:00:00": {
            "1. open": "67.2300",
            "2. high": "67.3500",
            "3. low": "67.1900",
            "4. close": "67.2900",
            "5. volume": "380686"
        },
        "2025-12-09 13:00:00": {
            "1. open": "67.2700",
            "2. high": "67.3100",
            "3. low": "66.9257",
            "4. close": "67.2400",
            "5. volume": "453300"
        },
        "2025-12-09 12:00:00": {
            "1. open": "67.1400",
            "2. high": "67.4900",
            "3. low": "67.0850",
            "4. close": "67.2750",
            "5. volume": "477636"
        },
        "2025-12-09 11:00:00": {
            "1. open": "67.3300",
            "2. high": "67.4600",
            "3. low": "66.9700",
            "4. close": "67.1500",
            "5. volume": "625274"
        },
        "2025-12-09 10:00:00": {
            "1. open": "66.6600",
            "2. high": "67.3400",
            "3. low": "66.5300",
            "4. close": "67.3200",
            "5. volume": "758624"
        },
        "2025-12-08 15:00:00": {
            "1. open": "66.7700",
            "2. high": "67.4200",
            "3. low": "66.7700",
            "4. close": "67.3500",
            "5. volume": "1809040"
        },
        "2025-12-08 14:00:00": {
            "1. open": "66.5700",
            "2. high": "66.9500",
            "3. low": "66.4700",
            "4. close": "66.7800",
            "5. volume": "756628"
        },
        "2025-12-08 13:00:00": {
            "1. open": "67.0800",
            "2. high": "67.1950",
            "3. low": "66.4200",
            "4. close": "66.5650",
            "5. volume": "796018"
        },
        "2025-12-08 12:00:00": {
            "1. open": "67.0900",
            "2. high": "67.4200",
            "3. low": "66.6300",
            "4. close": "67.0900",
            "5. volume": "792845"
        },
        "2025-12-08 11:00:00": {
            "1. open": "67.0100",
            "2. high": "67.3800",
            "3. low": "66.7500",
            "4. close": "67.1000",
            "5. volume": "704451"
        },
        "2025-12-08 10:00:00": {
            "1. open": "66.8700",
            "2. high": "67.4000",
            "3. low": "66.7300",
            "4. close": "67.0100",
            "5. volume": "1211824"
        },
        "2025-12-19 15:00:00": {
            "1. open": "64.6850",
            "2. high": "65.1300",
            "3. low": "64.6200",
            "4. close": "64.9200",
            "5. volume": "2679721"
        },
        "2025-12-19 14:00:00": {
            "1. open": "64.6100",
            "2. high": "64.7350",
            "3. low": "64.5400",
            "4. close": "64.6850",
            "5. volume": "557629"
        },
        "2025-12-19 13:00:00": {
            "1. open": "64.6600",
            "2. high": "64.9300",
            "3. low": "64.4700",
            "4. close": "64.6100",
            "5. volume": "510864"
        },
        "2025-12-19 12:00:00": {
            "1. open": "64.4000",
            "2. high": "64.9200",
            "3. low": "64.3800",
            "4. close": "64.6700",
            "5. volume": "673646"
        },
        "2025-12-19 11:00:00": {
            "1. open": "64.3000",
            "2. high": "64.6100",
            "3. low": "64.2100",
            "4. close": "64.3900",
            "5. volume": "464207"
        },
        "2025-12-19 10:00:00": {
            "1. open": "64.8300",
            "2. high": "64.9500",
            "3. low": "64.1100",
            "4. close": "64.3000",
            "5. volume": "596696"
        },
        "2025-12-18 15:00:00": {
            "1. open": "64.3400",
            "2. high": "64.7600",
            "3. low": "64.0100",
            "4. close": "64.0200",
            "5. volume": "1284775"
        },
        "2025-12-18 14:00:00": {
            "1. open": "64.7700",
            "2. high": "64.7700",
            "3. low": "64.2600",
            "4. close": "64.3200",
            "5. volume": "450506"
        },
        "2025-12-18 13:00:00": {
            "1. open": "64.8200",
            "2. high": "64.9700",
            "3. low": "64.6700",
            "4. close": "64.7550",
            "5. volume": "350773"
        },
        "2025-12-18 12:00:00": {
            "1. open": "64.7900",
            "2. high": "64.9000",
            "3. low": "64.1700",
            "4. close": "64.8000",
            "5. volume": "484847"
        },
        "2025-12-18 11:00:00": {
            "1. open": "64.7000",
            "2. high": "65.0000",
            "3. low": "64.6100",
            "4. close": "64.7900",
            "5. volume": "477872"
        },
        "2025-12-18 10:00:00": {
            "1. open": "64.7300",
            "2. high": "65.1000",
            "3. low": "63.7500",
            "4. close": "64.6850",
            "5. volume": "692035"
        },
        "2025-12-17 15:00:00": {
            "1. open": "63.8600",
            "2. high": "64.0500",
            "3. low": "63.4350",
            "4. close": "64.0300",
            "5. volume": "2193618"
        },
        "2025-12-17 14:00:00": {
            "1. open": "63.9100",
            "2. high": "63.9800",
            "3. low": "63.6500",
            "4. close": "63.8600",
            "5. volume": "691303"
        },
        "2025-12-17 13:00:00": {
            "1. open": "63.9450",
            "2. high": "64.1800",
            "3. low": "63.6301",
            "4. close": "63.8800",
            "5. volume": "511462"
        },
        "2025-12-17 12:00:00": {
            "1. open": "64.2950",
            "2. high": "64.4300",
            "3. low": "63.8200",
            "4. close": "63.9450",
            "5. volume": "601646"
        },
        "2025-12-17 11:00:00": {
            "1. open": "64.5600",
            "2. high": "65.0000",
            "3. low": "64.0100",
            "4. close": "64.2900",
            "5. volume": "600500"
        },
        "2025-12-17 10:00:00": {
            "1. open": "66.2700",
            "2. high": "66.4100",
            "3. low": "64.4700",
            "4. close": "64.6000",
            "5. volume": "587487"
        },
        "2025-12-16 15:00:00": {
            "1. open": "65.6300",
            "2. high": "66.1500",
            "3. low": "65.5700",
            "4. close": "65.8700",
            "5. volume": "1367603"
        },
        "2025-12-16 14:00:00": {
            "1. open": "65.4200",
            "2. high": "65.8700",
            "3. low": "65.1500",
            "4. close": "65.6550",
            "5. volume": "492855"
        },
        "2025-12-16 13:00:00": {
            "1. open": "65.7200",
            "2. high": "65.8700",
            "3. low": "65.3200",
            "4. close": "65.4400",
            "5. volume": "466106"
        },
        "2025-12-16 12:00:00": {
            "1. open": "66.5700",
            "2. high": "66.6400",
            "3. low": "64.9100",
            "4. close": "65.7056",
            "5. volume": "743194"
        },
        "2025-12-16 11:00:00": {
            "1. open": "66.6600",
            "2. high": "66.8400",
            "3. low": "66.2000",
            "4. close": "66.5700",
            "5. volume": "447277"
        },
        "2025-12-16 10:00:00": {
            "1. open": "67.6800",
            "2. high": "67.6800",
            "3. low": "66.0900",
            "4. close": "66.6716",
            "5. volume": "604503"
        }
    }
}